{"ok":1,"data":{"cards":[{"show_type":0,"title":"\u5b9e\u65f6\u70ed\u70b9\uff0c\u6bcf\u5206\u949f\u66f4\u65b0\u4e00\u6b21","card_type":11,"itemid":"hotword","card_group":[{"card_type":4,"pic":"https:\/\/simg.s.weibo.com\/20180205110043_img_search_stick%403x.png","itemid":"hotword","actionlog":{"act_code":554,"ext":"t:51|pos:0_0|cate:10113|c_type:51|page:1|type:25","luicode":"","fid":"106003type=25&t=3&disable_hot=1&filter_type=realtimehot","lfid":"","uicode":""},"scheme":"https:\/\/m.weibo.cn\/search?containerid=100103type%3D1%26t%3D10%26q%3D%232020%E5%B9%B4%E4%B8%AD%E5%9B%BD%E5%9F%8E%E9%95%87%E6%96%B0%E5%A2%9E%E5%B0%B1%E4%B8%9A1186%E4%B8%87%E4%BA%BA%23&isnewpage=1&extparam=seat%3D1%26pos%3D0%26c_type%3D51%26filter_type%3Drealtimehot%26cate%3D10103%26display_time%3D1610961193&luicode=10000011&lfid=106003type%3D25%26t%3D3%26disable_hot%3D1%26filter_type%3Drealtimehot","desc":"2020\u5e74\u4e2d\u56fd\u57ce\u9547\u65b0\u589e\u5c31\u4e1a1186\u4e07\u4eba","icon":"https:\/\/simg.s.weibo.com\/20200928_hot.png"},{"actionlog":{"act_code":554,"ext":"t:31|pos:1_0|cate:10103|c_type:31|page:1|type:25","luicode":"","fid":"106003type=25&t=3&disable_hot=1&filter_type=realtimehot","lfid":"","uicode":""},"itemid":"hotword","icon":"https:\/\/simg.s.weibo.com\/20200928_boom.png","desc_extr":11973735,"card_type":4,"scheme":"https:\/\/m.weibo.cn\/search?containerid=100103type%3D1%26t%3D10%26q%3D%23%E5%BC%A0%E6%81%92%E5%8F%91%E6%96%87%23&isnewpage=1&extparam=seat%3D1%26filter_type%3Drealtimehot%26cate%3D0%26pos%3D0%26realpos%3D1%26flag%3D4%26c_type%3D31%26display_time%3D1610961193&luicode=10000011&lfid=106003type%3D25%26t%3D3%26disable_hot%3D1%26filter_type%3Drealtimehot","desc":"\u5f20\u6052\u53d1\u6587","pic":"https:\/\/simg.s.weibo.com\/20170303_img_search_1.png"},{"card_type":4,"desc_extr":4755955,"itemid":"hotword","actionlog":{"act_code":554,"ext":"t:31|pos:1_1|cate:10103|c_type:31|page:1|type:25","luicode":"","fid":"106003type=25&t=3&disable_hot=1&filter_type=realtimehot","lfid":"","uicode":""},"scheme":"https:\/\/m.weibo.cn\/search?containerid=100103type%3D1%26t%3D10%26q%3D%E7%89%B9%E6%9C%97%E6%99%AE%E7%A6%BB%E4%BB%BB%E5%89%8D%E5%B0%86%E5%8F%91%E5%B8%83100%E9%A1%B9%E7%89%B9%E8%B5%A6%E5%92%8C%E5%87%8F%E5%88%91%E4%BB%A4&isnewpage=1&extparam=seat%3D1%26filter_type%3Drealtimehot%26cate%3D0%26pos%3D1%26realpos%3D2%26flag%3D0%26c_type%3D31%26display_time%3D1610961193&luicode=10000011&lfid=106003type%3D25%26t%3D3%26disable_hot%3D1%26filter_type%3Drealtimehot","desc":"\u7279\u6717\u666e\u79bb\u4efb\u524d\u5c06\u53d1\u5e03100\u9879\u7279\u8d66\u548c\u51cf\u5211\u4ee4","pic":"https:\/\/simg.s.weibo.com\/20170303_img_search_2.png"},{"actionlog":{"act_code":554,"ext":"t:31|pos:1_2|ads_word:#\u9ec4\u5b50\u97ec\u5c0f\u5965\u6c40\u6f6e\u73a9\u5408\u4f19\u4eba#|c_type:31|cate:10103|adid:109952|page:1|type:25","luicode":"","fid":"106003type=25&t=3&disable_hot=1&filter_type=realtimehot","lfid":"","uicode":""},"itemid":"hotword","icon":"https:\/\/simg.s.weibo.com\/20200928_jian.png","desc_extr":4697772,"promotion":{"monitor_url":[]},"card_type":4,"scheme":"https:\/\/m.weibo.cn\/search?containerid=100103type%3D1%26t%3D10%26q%3D%23%E9%BB%84%E5%AD%90%E9%9F%AC%E5%B0%8F%E5%A5%A5%E6%B1%80%E6%BD%AE%E7%8E%A9%E5%90%88%E4%BC%99%E4%BA%BA%23&isnewpage=1&extparam=seat%3D1%26filter_type%3Drealtimehot%26cate%3D0%26topic_ad%3D1%26pos%3D2%26c_type%3D31%26adid%3D109952%26display_time%3D1610961193&luicode=10000011&lfid=106003type%3D25%26t%3D3%26disable_hot%3D1%26filter_type%3Drealtimehot","desc":"\u9ec4\u5b50\u97ec\u5c0f\u5965\u6c40\u6f6e\u73a9\u5408\u4f19\u4eba","pic":"https:\/\/simg.s.weibo.com\/20170303_img_search_3.png"},{"actionlog":{"act_code":554,"ext":"t:31|pos:1_3|cate:10103|c_type:31|page:1|type:25","luicode":"","fid":"106003type=25&t=3&disable_hot=1&filter_type=realtimehot","lfid":"","uicode":""},"itemid":"hotword","icon":"https:\/\/simg.s.weibo.com\/20200928_fei.png","desc_extr":4432715,"card_type":4,"scheme":"https:\/\/m.weibo.cn\/search?containerid=100103type%3D1%26t%3D10%26q%3D%E9%83%91%E7%88%BD%E5%BC%A0%E6%81%92%E5%AD%A9%E5%AD%90%E5%87%BA%E7%94%9F%E8%AF%81%E6%98%8E&isnewpage=1&extparam=seat%3D1%26filter_type%3Drealtimehot%26cate%3D0%26pos%3D3%26realpos%3D3%26flag%3D16%26c_type%3D31%26display_time%3D1610961193&luicode=10000011&lfid=106003type%3D25%26t%3D3%26disable_hot%3D1%26filter_type%3Drealtimehot","desc":"\u90d1\u723d\u5f20\u6052\u5b69\u5b50\u51fa\u751f\u8bc1\u660e","pic":"https:\/\/simg.s.weibo.com\/20170303_img_search_4.png"},{"actionlog":{"act_code":554,"ext":"t:31|pos:1_4|cate:10103|c_type:31|page:1|type:25","luicode":"","fid":"106003type=25&t=3&disable_hot=1&filter_type=realtimehot","lfid":"","uicode":""},"itemid":"hotword","icon":"https:\/\/simg.s.weibo.com\/20200928_new.png","desc_extr":2663065,"card_type":4,"scheme":"https:\/\/m.weibo.cn\/search?containerid=100103type%3D1%26t%3D10%26q%3DPrada%E8%82%A1%E7%A5%A8%E4%B8%8B%E8%B7%8C&isnewpage=1&extparam=seat%3D1%26filter_type%3Drealtimehot%26cate%3D0%26pos%3D4%26realpos%3D4%26flag%3D1%26c_type%3D31%26display_time%3D1610961193&luicode=10000011&lfid=106003type%3D25%26t%3D3%26disable_hot%3D1%26filter_type%3Drealtimehot","desc":"Prada\u80a1\u7968\u4e0b\u8dcc","pic":"https:\/\/simg.s.weibo.com\/20170303_img_search_5.png"},{"actionlog":{"act_code":554,"ext":"t:31|pos:1_5|ads_word:#\u5fae\u535aking\u548cqueen\u8bde\u751f#|c_type:31|cate:10103|adid:109984|page:1|type:25","luicode":"","fid":"106003type=25&t=3&disable_hot=1&filter_type=realtimehot","lfid":"","uicode":""},"itemid":"hotword","icon":"https:\/\/simg.s.weibo.com\/20200928_jian_yellow.png","desc_extr":2342792,"promotion":{"monitor_url":[]},"card_type":4,"scheme":"https:\/\/m.weibo.cn\/search?containerid=100103type%3D1%26t%3D10%26q%3D%23%E5%BE%AE%E5%8D%9Aking%E5%92%8Cqueen%E8%AF%9E%E7%94%9F%23&isnewpage=1&extparam=seat%3D1%26filter_type%3Drealtimehot%26cate%3D0%26pos%3D5%26c_type%3D31%26adid%3D109984%26display_time%3D1610961193&luicode=10000011&lfid=106003type%3D25%26t%3D3%26disable_hot%3D1%26filter_type%3Drealtimehot","desc":"\u5fae\u535aking\u548cqueen\u8bde\u751f","pic":"https:\/\/simg.s.weibo.com\/20170303_img_search_6.png"},{"actionlog":{"act_code":554,"ext":"t:31|pos:1_6|cate:10103|c_type:31|page:1|type:25","luicode":"","fid":"106003type=25&t=3&disable_hot=1&filter_type=realtimehot","lfid":"","uicode":""},"itemid":"hotword","icon":"https:\/\/simg.s.weibo.com\/20200928_fei.png","desc_extr":2262723,"card_type":4,"scheme":"https:\/\/m.weibo.cn\/search?containerid=100103type%3D1%26t%3D10%26q%3D%23%E5%BE%AE%E4%BF%A1bug%23&isnewpage=1&extparam=seat%3D1%26filter_type%3Drealtimehot%26cate%3D0%26pos%3D6%26realpos%3D5%26flag%3D16%26c_type%3D31%26display_time%3D1610961193&luicode=10000011&lfid=106003type%3D25%26t%3D3%26disable_hot%3D1%26filter_type%3Drealtimehot","desc":"\u5fae\u4fe1bug","pic":"https:\/\/simg.s.weibo.com\/20170303_img_search_7.png"},{"actionlog":{"act_code":554,"ext":"t:31|pos:1_7|cate:10103|c_type:31|page:1|type:25","luicode":"","fid":"106003type=25&t=3&disable_hot=1&filter_type=realtimehot","lfid":"","uicode":""},"itemid":"hotword","icon":"https:\/\/simg.s.weibo.com\/20200928_new.png","desc_extr":1470054,"card_type":4,"scheme":"https:\/\/m.weibo.cn\/search?containerid=100103type%3D1%26t%3D10%26q%3D%23%E5%BE%AE%E4%BF%A1%E5%9B%9E%E5%BA%94%E6%B6%88%E6%81%AF%E5%BB%B6%E8%BF%9Fbug%23&isnewpage=1&extparam=seat%3D1%26filter_type%3Drealtimehot%26cate%3D0%26pos%3D7%26realpos%3D6%26flag%3D1%26c_type%3D31%26display_time%3D1610961193&luicode=10000011&lfid=106003type%3D25%26t%3D3%26disable_hot%3D1%26filter_type%3Drealtimehot","desc":"\u5fae\u4fe1\u56de\u5e94\u6d88\u606f\u5ef6\u8fdfbug","pic":"https:\/\/simg.s.weibo.com\/20170303_img_search_8.png"},{"actionlog":{"act_code":554,"ext":"t:31|pos:1_8|cate:10103|c_type:31|page:1|type:25","luicode":"","fid":"106003type=25&t=3&disable_hot=1&filter_type=realtimehot","lfid":"","uicode":""},"itemid":"hotword","icon":"https:\/\/simg.s.weibo.com\/20200928_fei.png","desc_extr":1152560,"card_type":4,"scheme":"https:\/\/m.weibo.cn\/search?containerid=100103type%3D1%26t%3D10%26q%3D%E5%9F%BA%E9%87%91&isnewpage=1&extparam=seat%3D1%26filter_type%3Drealtimehot%26cate%3D0%26pos%3D8%26realpos%3D7%26flag%3D16%26c_type%3D31%26display_time%3D1610961193&luicode=10000011&lfid=106003type%3D25%26t%3D3%26disable_hot%3D1%26filter_type%3Drealtimehot","desc":"\u57fa\u91d1","pic":"https:\/\/simg.s.weibo.com\/20170303_img_search_9.png"},{"actionlog":{"act_code":554,"ext":"t:31|pos:1_9|cate:10103|c_type:31|page:1|type:25","luicode":"","fid":"106003type=25&t=3&disable_hot=1&filter_type=realtimehot","lfid":"","uicode":""},"itemid":"hotword","icon":"https:\/\/simg.s.weibo.com\/20200928_new.png","desc_extr":913535,"card_type":4,"scheme":"https:\/\/m.weibo.cn\/search?containerid=100103type%3D1%26t%3D10%26q%3D%23%E7%94%B7%E5%AD%90%E5%9C%A8%E6%B3%95%E5%BA%AD%E5%88%BA%E6%AD%BB%E6%B3%95%E5%AE%98%E8%A2%AB%E5%88%A4%E6%AD%BB%E5%88%91%23&isnewpage=1&extparam=seat%3D1%26filter_type%3Drealtimehot%26cate%3D0%26pos%3D9%26realpos%3D8%26flag%3D1%26c_type%3D31%26display_time%3D1610961193&luicode=10000011&lfid=106003type%3D25%26t%3D3%26disable_hot%3D1%26filter_type%3Drealtimehot","desc":"\u7537\u5b50\u5728\u6cd5\u5ead\u523a\u6b7b\u6cd5\u5b98\u88ab\u5224\u6b7b\u5211","pic":"https:\/\/simg.s.weibo.com\/20170303_img_search_10.png"},{"actionlog":{"act_code":554,"ext":"t:31|pos:1_10|cate:10103|c_type:31|page:1|type:25","luicode":"","fid":"106003type=25&t=3&disable_hot=1&filter_type=realtimehot","lfid":"","uicode":""},"itemid":"hotword","icon":"https:\/\/simg.s.weibo.com\/20200928_hot.png","desc_extr":863794,"card_type":4,"scheme":"https:\/\/m.weibo.cn\/search?containerid=100103type%3D1%26t%3D10%26q%3D%2362%E5%B2%81%E5%88%98%E8%8A%B8%E5%A6%88%E5%A6%88%E7%8A%B6%E6%80%81%23&isnewpage=1&extparam=seat%3D1%26filter_type%3Drealtimehot%26cate%3D0%26pos%3D10%26realpos%3D9%26flag%3D2%26c_type%3D31%26display_time%3D1610961193&luicode=10000011&lfid=106003type%3D25%26t%3D3%26disable_hot%3D1%26filter_type%3Drealtimehot","desc":"62\u5c81\u5218\u82b8\u5988\u5988\u72b6\u6001","pic":"https:\/\/simg.s.weibo.com\/20170303_img_search_11.png"},{"actionlog":{"act_code":554,"ext":"t:31|pos:1_11|cate:10103|c_type:31|page:1|type:25","luicode":"","fid":"106003type=25&t=3&disable_hot=1&filter_type=realtimehot","lfid":"","uicode":""},"itemid":"hotword","icon":"https:\/\/simg.s.weibo.com\/20200928_hot.png","desc_extr":850748,"card_type":4,"scheme":"https:\/\/m.weibo.cn\/search?containerid=100103type%3D1%26t%3D10%26q%3D%E5%82%85%E8%8F%81+%E6%88%91%E7%9A%84%E8%85%BF%E4%B8%8D%E6%98%AF%E5%BE%88%E5%AE%8C%E7%BE%8E&isnewpage=1&extparam=seat%3D1%26filter_type%3Drealtimehot%26cate%3D0%26pos%3D11%26realpos%3D10%26flag%3D2%26c_type%3D31%26display_time%3D1610961193&luicode=10000011&lfid=106003type%3D25%26t%3D3%26disable_hot%3D1%26filter_type%3Drealtimehot","desc":"\u5085\u83c1 \u6211\u7684\u817f\u4e0d\u662f\u5f88\u5b8c\u7f8e","pic":"https:\/\/simg.s.weibo.com\/20170303_img_search_12.png"},{"actionlog":{"act_code":554,"ext":"t:31|pos:1_12|cate:10103|c_type:31|page:1|type:25","luicode":"","fid":"106003type=25&t=3&disable_hot=1&filter_type=realtimehot","lfid":"","uicode":""},"itemid":"hotword","icon":"https:\/\/simg.s.weibo.com\/20200928_hot.png","desc_extr":442681,"card_type":4,"scheme":"https:\/\/m.weibo.cn\/search?containerid=100103type%3D1%26t%3D10%26q%3D%23%E6%9E%97%E7%8F%8A%E7%8F%8A%E5%A4%A7%E7%99%BD%E7%A6%BB%E5%A9%9A%23&isnewpage=1&extparam=seat%3D1%26filter_type%3Drealtimehot%26cate%3D0%26pos%3D12%26realpos%3D11%26flag%3D2%26c_type%3D31%26display_time%3D1610961193&luicode=10000011&lfid=106003type%3D25%26t%3D3%26disable_hot%3D1%26filter_type%3Drealtimehot","desc":"\u6797\u73ca\u73ca\u5927\u767d\u79bb\u5a5a","pic":"https:\/\/simg.s.weibo.com\/20170303_img_search_13.png"},{"card_type":4,"desc_extr":415862,"itemid":"hotword","actionlog":{"act_code":554,"ext":"t:31|pos:1_13|cate:10103|c_type:31|page:1|type:25","luicode":"","fid":"106003type=25&t=3&disable_hot=1&filter_type=realtimehot","lfid":"","uicode":""},"scheme":"https:\/\/m.weibo.cn\/search?containerid=100103type%3D1%26t%3D10%26q%3D%23%E7%8E%8B%E7%89%8C%E5%AF%B9%E7%8E%8B%E7%89%8C%E5%AE%9A%E6%A1%A3%23&isnewpage=1&extparam=seat%3D1%26filter_type%3Drealtimehot%26cate%3D0%26pos%3D13%26realpos%3D12%26flag%3D0%26c_type%3D31%26display_time%3D1610961193&luicode=10000011&lfid=106003type%3D25%26t%3D3%26disable_hot%3D1%26filter_type%3Drealtimehot","desc":"\u738b\u724c\u5bf9\u738b\u724c\u5b9a\u6863","pic":"https:\/\/simg.s.weibo.com\/20170303_img_search_14.png"},{"actionlog":{"act_code":554,"ext":"t:31|pos:1_14|cate:10103|c_type:31|page:1|type:25","luicode":"","fid":"106003type=25&t=3&disable_hot=1&filter_type=realtimehot","lfid":"","uicode":""},"itemid":"hotword","icon":"https:\/\/simg.s.weibo.com\/20200928_hot.png","desc_extr":414399,"card_type":4,"scheme":"https:\/\/m.weibo.cn\/search?containerid=100103type%3D1%26t%3D10%26q%3D%23%E5%8C%97%E4%BA%AC%E7%A1%AE%E8%AF%8A6%E5%B2%81%E7%94%B7%E7%AB%A5%E6%9B%BE%E5%9C%A8%E5%B0%8F%E9%A5%AD%E6%A1%8C%E6%89%98%E7%AE%A1%23&isnewpage=1&extparam=seat%3D1%26filter_type%3Drealtimehot%26cate%3D0%26pos%3D14%26realpos%3D13%26flag%3D2%26c_type%3D31%26display_time%3D1610961193&luicode=10000011&lfid=106003type%3D25%26t%3D3%26disable_hot%3D1%26filter_type%3Drealtimehot","desc":"\u5317\u4eac\u786e\u8bca6\u5c81\u7537\u7ae5\u66fe\u5728\u5c0f\u996d\u684c\u6258\u7ba1","pic":"https:\/\/simg.s.weibo.com\/20170303_img_search_15.png"},{"card_type":4,"desc_extr":413397,"itemid":"hotword","actionlog":{"act_code":554,"ext":"t:31|pos:1_15|cate:10103|c_type:31|page:1|type:25","luicode":"","fid":"106003type=25&t=3&disable_hot=1&filter_type=realtimehot","lfid":"","uicode":""},"scheme":"https:\/\/m.weibo.cn\/search?containerid=100103type%3D1%26t%3D10%26q%3D%E6%9D%8E%E5%9C%A8%E9%95%95%E8%8E%B7%E5%88%912%E5%B9%B4%E5%8D%8A&isnewpage=1&extparam=seat%3D1%26filter_type%3Drealtimehot%26cate%3D0%26pos%3D15%26realpos%3D14%26flag%3D0%26c_type%3D31%26display_time%3D1610961193&luicode=10000011&lfid=106003type%3D25%26t%3D3%26disable_hot%3D1%26filter_type%3Drealtimehot","desc":"\u674e\u5728\u9555\u83b7\u52112\u5e74\u534a","pic":"https:\/\/simg.s.weibo.com\/20170303_img_search_16.png"},{"card_type":4,"desc_extr":413232,"itemid":"hotword","actionlog":{"act_code":554,"ext":"t:31|pos:1_16|cate:10103|c_type:31|page:1|type:25","luicode":"","fid":"106003type=25&t=3&disable_hot=1&filter_type=realtimehot","lfid":"","uicode":""},"scheme":"https:\/\/m.weibo.cn\/search?containerid=100103type%3D1%26t%3D10%26q%3D%23%E4%BD%A0%E6%98%AF%E5%90%A6%E7%9C%8B%E5%88%B0%E4%BA%86%E4%B8%80%E5%8F%AA%E9%B8%A1%23&isnewpage=1&extparam=seat%3D1%26filter_type%3Drealtimehot%26cate%3D0%26pos%3D16%26realpos%3D15%26flag%3D0%26c_type%3D31%26display_time%3D1610961193&luicode=10000011&lfid=106003type%3D25%26t%3D3%26disable_hot%3D1%26filter_type%3Drealtimehot","desc":"\u4f60\u662f\u5426\u770b\u5230\u4e86\u4e00\u53ea\u9e21","pic":"https:\/\/simg.s.weibo.com\/20170303_img_search_17.png"},{"actionlog":{"act_code":554,"ext":"t:31|pos:1_17|cate:10103|c_type:31|page:1|type:25","luicode":"","fid":"106003type=25&t=3&disable_hot=1&filter_type=realtimehot","lfid":"","uicode":""},"itemid":"hotword","icon":"https:\/\/simg.s.weibo.com\/20200928_new.png","desc_extr":412966,"card_type":4,"scheme":"https:\/\/m.weibo.cn\/search?containerid=100103type%3D1%26t%3D10%26q%3D%E9%83%91%E7%88%BD%E8%B6%85%E8%AF%9D&isnewpage=1&extparam=seat%3D1%26filter_type%3Drealtimehot%26cate%3D0%26pos%3D17%26realpos%3D16%26flag%3D1%26c_type%3D31%26display_time%3D1610961193&luicode=10000011&lfid=106003type%3D25%26t%3D3%26disable_hot%3D1%26filter_type%3Drealtimehot","desc":"\u90d1\u723d\u8d85\u8bdd","pic":"https:\/\/simg.s.weibo.com\/20170303_img_search_18.png"},{"actionlog":{"act_code":554,"ext":"t:31|pos:1_18|cate:10103|c_type:31|page:1|type:25","luicode":"","fid":"106003type=25&t=3&disable_hot=1&filter_type=realtimehot","lfid":"","uicode":""},"itemid":"hotword","icon":"https:\/\/simg.s.weibo.com\/20200928_new.png","desc_extr":412450,"card_type":4,"scheme":"https:\/\/m.weibo.cn\/search?containerid=100103type%3D1%26t%3D10%26q%3D%23%E8%BE%9B%E8%8A%B7%E8%95%BE%E7%82%B9%E8%B5%9E%23&isnewpage=1&extparam=seat%3D1%26filter_type%3Drealtimehot%26cate%3D0%26pos%3D18%26realpos%3D17%26flag%3D1%26c_type%3D31%26display_time%3D1610961193&luicode=10000011&lfid=106003type%3D25%26t%3D3%26disable_hot%3D1%26filter_type%3Drealtimehot","desc":"\u8f9b\u82b7\u857e\u70b9\u8d5e","pic":"https:\/\/simg.s.weibo.com\/20170303_img_search_19.png"},{"card_type":4,"desc_extr":412005,"itemid":"hotword","actionlog":{"act_code":554,"ext":"t:31|pos:1_19|cate:10103|c_type:31|page:1|type:25","luicode":"","fid":"106003type=25&t=3&disable_hot=1&filter_type=realtimehot","lfid":"","uicode":""},"scheme":"https:\/\/m.weibo.cn\/search?containerid=100103type%3D1%26t%3D10%26q%3D%23%E4%B8%8A%E6%B5%B7%E5%85%AC%E4%BA%A4%E8%BD%A6%E6%80%A5%E5%88%B9%E8%87%B4%E4%B8%80%E5%A5%B3%E5%AD%90%E6%AD%BB%E4%BA%A1%23&isnewpage=1&extparam=seat%3D1%26filter_type%3Drealtimehot%26cate%3D0%26pos%3D19%26realpos%3D18%26flag%3D0%26c_type%3D31%26display_time%3D1610961193&luicode=10000011&lfid=106003type%3D25%26t%3D3%26disable_hot%3D1%26filter_type%3Drealtimehot","desc":"\u4e0a\u6d77\u516c\u4ea4\u8f66\u6025\u5239\u81f4\u4e00\u5973\u5b50\u6b7b\u4ea1","pic":"https:\/\/simg.s.weibo.com\/20170303_img_search_20.png"},{"actionlog":{"act_code":554,"ext":"t:31|pos:1_20|cate:10103|c_type:31|page:1|type:25","luicode":"","fid":"106003type=25&t=3&disable_hot=1&filter_type=realtimehot","lfid":"","uicode":""},"itemid":"hotword","icon":"https:\/\/simg.s.weibo.com\/20200928_new.png","desc_extr":411615,"card_type":4,"scheme":"https:\/\/m.weibo.cn\/search?containerid=100103type%3D1%26t%3D10%26q%3D%E6%B1%AA%E5%B3%B0&isnewpage=1&extparam=seat%3D1%26filter_type%3Drealtimehot%26cate%3D0%26pos%3D20%26realpos%3D19%26flag%3D1%26c_type%3D31%26display_time%3D1610961193&luicode=10000011&lfid=106003type%3D25%26t%3D3%26disable_hot%3D1%26filter_type%3Drealtimehot","desc":"\u6c6a\u5cf0","pic":"https:\/\/simg.s.weibo.com\/20170303_img_search_21.png"},{"actionlog":{"act_code":554,"ext":"t:31|pos:1_21|cate:10103|c_type:31|page:1|type:25","luicode":"","fid":"106003type=25&t=3&disable_hot=1&filter_type=realtimehot","lfid":"","uicode":""},"itemid":"hotword","icon":"https:\/\/simg.s.weibo.com\/20200928_new.png","desc_extr":411066,"card_type":4,"scheme":"https:\/\/m.weibo.cn\/search?containerid=100103type%3D1%26t%3D10%26q%3D%23%E5%AD%99%E6%80%A1%E5%AE%B6%E7%9A%84%E5%B0%8F%E9%B8%A1%E8%A2%AB%E9%87%8E%E7%8C%AB%E7%BB%99%E5%8F%BC%E8%B5%B0%E4%BA%86%23&isnewpage=1&extparam=seat%3D1%26filter_type%3Drealtimehot%26cate%3D0%26pos%3D21%26realpos%3D20%26flag%3D1%26c_type%3D31%26display_time%3D1610961193&luicode=10000011&lfid=106003type%3D25%26t%3D3%26disable_hot%3D1%26filter_type%3Drealtimehot","desc":"\u5b59\u6021\u5bb6\u7684\u5c0f\u9e21\u88ab\u91ce\u732b\u7ed9\u53fc\u8d70\u4e86","pic":"https:\/\/simg.s.weibo.com\/20170303_img_search_22.png"},{"actionlog":{"act_code":554,"ext":"t:31|pos:1_22|cate:10103|c_type:31|page:1|type:25","luicode":"","fid":"106003type=25&t=3&disable_hot=1&filter_type=realtimehot","lfid":"","uicode":""},"itemid":"hotword","icon":"https:\/\/simg.s.weibo.com\/20200928_new.png","desc_extr":410912,"card_type":4,"scheme":"https:\/\/m.weibo.cn\/search?containerid=100103type%3D1%26t%3D10%26q%3D%E5%8C%97%E4%BA%AC%E7%94%B5%E8%A7%86%E5%8F%B0%E7%BB%99%E9%83%91%E7%88%BD%E5%8A%A0%E6%B2%B9&isnewpage=1&extparam=seat%3D1%26filter_type%3Drealtimehot%26cate%3D0%26pos%3D22%26realpos%3D21%26flag%3D1%26c_type%3D31%26display_time%3D1610961193&luicode=10000011&lfid=106003type%3D25%26t%3D3%26disable_hot%3D1%26filter_type%3Drealtimehot","desc":"\u5317\u4eac\u7535\u89c6\u53f0\u7ed9\u90d1\u723d\u52a0\u6cb9","pic":"https:\/\/simg.s.weibo.com\/20170303_img_search_23.png"},{"card_type":4,"desc_extr":410460,"itemid":"hotword","actionlog":{"act_code":554,"ext":"t:31|pos:1_23|cate:10103|c_type:31|page:1|type:25","luicode":"","fid":"106003type=25&t=3&disable_hot=1&filter_type=realtimehot","lfid":"","uicode":""},"scheme":"https:\/\/m.weibo.cn\/search?containerid=100103type%3D1%26t%3D10%26q%3D%E6%96%B0%E5%86%A0%E7%96%AB%E8%8B%97&isnewpage=1&extparam=seat%3D1%26filter_type%3Drealtimehot%26cate%3D0%26pos%3D23%26realpos%3D22%26flag%3D0%26c_type%3D31%26display_time%3D1610961193&luicode=10000011&lfid=106003type%3D25%26t%3D3%26disable_hot%3D1%26filter_type%3Drealtimehot","desc":"\u65b0\u51a0\u75ab\u82d7","pic":"https:\/\/simg.s.weibo.com\/20170303_img_search_24.png"},{"card_type":4,"desc_extr":409760,"itemid":"hotword","actionlog":{"act_code":554,"ext":"t:31|pos:1_24|cate:10103|c_type:31|page:1|type:25","luicode":"","fid":"106003type=25&t=3&disable_hot=1&filter_type=realtimehot","lfid":"","uicode":""},"scheme":"https:\/\/m.weibo.cn\/search?containerid=100103type%3D1%26t%3D10%26q%3D%E6%9C%B4%E6%A7%BF%E6%83%A0%E6%94%B6%E5%88%B0%E5%B7%A8%E9%A2%9D%E7%BD%9A%E6%AC%BE%E5%8D%95&isnewpage=1&extparam=seat%3D1%26filter_type%3Drealtimehot%26cate%3D0%26pos%3D24%26realpos%3D23%26flag%3D0%26c_type%3D31%26display_time%3D1610961193&luicode=10000011&lfid=106003type%3D25%26t%3D3%26disable_hot%3D1%26filter_type%3Drealtimehot","desc":"\u6734\u69ff\u60e0\u6536\u5230\u5de8\u989d\u7f5a\u6b3e\u5355","pic":"https:\/\/simg.s.weibo.com\/20170303_img_search_25.png"},{"card_type":4,"desc_extr":409707,"itemid":"hotword","actionlog":{"act_code":554,"ext":"t:31|pos:1_25|cate:10103|c_type:31|page:1|type:25","luicode":"","fid":"106003type=25&t=3&disable_hot=1&filter_type=realtimehot","lfid":"","uicode":""},"scheme":"https:\/\/m.weibo.cn\/search?containerid=100103type%3D1%26t%3D10%26q%3D%23%E6%9D%A8%E6%B4%8B%E8%BF%AA%E4%B8%BD%E7%83%AD%E5%B7%B4%E7%9C%BC%E7%A5%9E%E5%A5%BD%E7%94%9C%23&isnewpage=1&extparam=seat%3D1%26filter_type%3Drealtimehot%26cate%3D0%26pos%3D25%26realpos%3D24%26flag%3D0%26c_type%3D31%26display_time%3D1610961193&luicode=10000011&lfid=106003type%3D25%26t%3D3%26disable_hot%3D1%26filter_type%3Drealtimehot","desc":"\u6768\u6d0b\u8fea\u4e3d\u70ed\u5df4\u773c\u795e\u597d\u751c","pic":"https:\/\/simg.s.weibo.com\/20170303_img_search_26.png"},{"card_type":4,"desc_extr":409046,"itemid":"hotword","actionlog":{"act_code":554,"ext":"t:31|pos:1_26|cate:10103|c_type:31|page:1|type:25","luicode":"","fid":"106003type=25&t=3&disable_hot=1&filter_type=realtimehot","lfid":"","uicode":""},"scheme":"https:\/\/m.weibo.cn\/search?containerid=100103type%3D1%26t%3D10%26q%3D%23%E8%BF%9F%E5%88%B033%E5%B9%B4%E7%9A%84%E5%A9%9A%E7%BA%B1%E7%85%A7%23&isnewpage=1&extparam=seat%3D1%26filter_type%3Drealtimehot%26cate%3D0%26pos%3D26%26realpos%3D25%26flag%3D0%26c_type%3D31%26display_time%3D1610961193&luicode=10000011&lfid=106003type%3D25%26t%3D3%26disable_hot%3D1%26filter_type%3Drealtimehot","desc":"\u8fdf\u523033\u5e74\u7684\u5a5a\u7eb1\u7167","pic":"https:\/\/simg.s.weibo.com\/20170303_img_search_27.png"},{"card_type":4,"desc_extr":408941,"itemid":"hotword","actionlog":{"act_code":554,"ext":"t:31|pos:1_27|cate:10103|c_type:31|page:1|type:25","luicode":"","fid":"106003type=25&t=3&disable_hot=1&filter_type=realtimehot","lfid":"","uicode":""},"scheme":"https:\/\/m.weibo.cn\/search?containerid=100103type%3D1%26t%3D10%26q%3D%23%E5%A7%9A%E5%AE%89%E5%A8%9C%E5%8D%95%E6%9B%B2%23&isnewpage=1&extparam=seat%3D1%26filter_type%3Drealtimehot%26cate%3D0%26pos%3D27%26realpos%3D26%26flag%3D0%26c_type%3D31%26display_time%3D1610961193&luicode=10000011&lfid=106003type%3D25%26t%3D3%26disable_hot%3D1%26filter_type%3Drealtimehot","desc":"\u59da\u5b89\u5a1c\u5355\u66f2","pic":"https:\/\/simg.s.weibo.com\/20170303_img_search_28.png"},{"card_type":4,"desc_extr":394133,"itemid":"hotword","actionlog":{"act_code":554,"ext":"t:31|pos:1_28|cate:10103|c_type:31|page:1|type:25","luicode":"","fid":"106003type=25&t=3&disable_hot=1&filter_type=realtimehot","lfid":"","uicode":""},"scheme":"https:\/\/m.weibo.cn\/search?containerid=100103type%3D1%26t%3D10%26q%3D%E8%80%81%E8%99%8E%E5%92%AC%E4%BD%8F%E8%BD%A6%E5%B0%BE%E5%B0%86%E6%95%B4%E8%BD%A6%E4%BA%BA%E6%8B%96%E5%8A%A8%E6%95%B0%E7%B1%B3&isnewpage=1&extparam=seat%3D1%26filter_type%3Drealtimehot%26cate%3D0%26pos%3D28%26realpos%3D27%26flag%3D0%26c_type%3D31%26display_time%3D1610961193&luicode=10000011&lfid=106003type%3D25%26t%3D3%26disable_hot%3D1%26filter_type%3Drealtimehot","desc":"\u8001\u864e\u54ac\u4f4f\u8f66\u5c3e\u5c06\u6574\u8f66\u4eba\u62d6\u52a8\u6570\u7c73","pic":"https:\/\/simg.s.weibo.com\/20170303_img_search_29.png"},{"card_type":4,"desc_extr":355397,"itemid":"hotword","actionlog":{"act_code":554,"ext":"t:31|pos:1_29|cate:10103|c_type:31|page:1|type:25","luicode":"","fid":"106003type=25&t=3&disable_hot=1&filter_type=realtimehot","lfid":"","uicode":""},"scheme":"https:\/\/m.weibo.cn\/search?containerid=100103type%3D1%26t%3D10%26q%3D%23%E5%8D%8E%E4%B8%BA%E5%95%86%E5%9F%8E%E4%B8%8B%E6%9E%B6%E8%8D%A3%E8%80%80%E5%85%A8%E9%83%A8%E4%BA%A7%E5%93%81%23&isnewpage=1&extparam=seat%3D1%26filter_type%3Drealtimehot%26cate%3D0%26pos%3D29%26realpos%3D28%26flag%3D0%26c_type%3D31%26display_time%3D1610961193&luicode=10000011&lfid=106003type%3D25%26t%3D3%26disable_hot%3D1%26filter_type%3Drealtimehot","desc":"\u534e\u4e3a\u5546\u57ce\u4e0b\u67b6\u8363\u8000\u5168\u90e8\u4ea7\u54c1","pic":"https:\/\/simg.s.weibo.com\/20170303_img_search_30.png"},{"actionlog":{"act_code":554,"ext":"t:31|pos:1_30|cate:10103|c_type:31|page:1|type:25","luicode":"","fid":"106003type=25&t=3&disable_hot=1&filter_type=realtimehot","lfid":"","uicode":""},"itemid":"hotword","icon":"https:\/\/simg.s.weibo.com\/20200928_new.png","desc_extr":351660,"card_type":4,"scheme":"https:\/\/m.weibo.cn\/search?containerid=100103type%3D1%26t%3D10%26q%3D%23%E6%B5%8E%E5%8D%97%E5%A4%A7%E6%98%8E%E6%B9%96%E7%AB%99%23&isnewpage=1&extparam=seat%3D1%26filter_type%3Drealtimehot%26cate%3D0%26pos%3D30%26realpos%3D29%26flag%3D1%26c_type%3D31%26display_time%3D1610961193&luicode=10000011&lfid=106003type%3D25%26t%3D3%26disable_hot%3D1%26filter_type%3Drealtimehot","desc":"\u6d4e\u5357\u5927\u660e\u6e56\u7ad9","pic":"https:\/\/simg.s.weibo.com\/20170303_img_search_31.png"},{"card_type":4,"desc_extr":350136,"itemid":"hotword","actionlog":{"act_code":554,"ext":"t:31|pos:1_31|cate:10103|c_type:31|page:1|type:25","luicode":"","fid":"106003type=25&t=3&disable_hot=1&filter_type=realtimehot","lfid":"","uicode":""},"scheme":"https:\/\/m.weibo.cn\/search?containerid=100103type%3D1%26t%3D10%26q%3D%23%E8%BF%98%E8%B4%B77%E5%B9%B4%E5%A4%9A117%E4%B8%87%E6%9C%AC%E9%87%91%E7%AB%9F%E7%84%B6%E4%B8%80%E5%88%86%E9%83%BD%E6%B2%A1%E8%BF%98%23&isnewpage=1&extparam=seat%3D1%26filter_type%3Drealtimehot%26cate%3D0%26pos%3D31%26realpos%3D30%26flag%3D0%26c_type%3D31%26display_time%3D1610961193&luicode=10000011&lfid=106003type%3D25%26t%3D3%26disable_hot%3D1%26filter_type%3Drealtimehot","desc":"\u8fd8\u8d377\u5e74\u591a117\u4e07\u672c\u91d1\u7adf\u7136\u4e00\u5206\u90fd\u6ca1\u8fd8","pic":"https:\/\/simg.s.weibo.com\/20170303_img_search_32.png"},{"card_type":4,"desc_extr":343183,"itemid":"hotword","actionlog":{"act_code":554,"ext":"t:31|pos:1_32|cate:10103|c_type:31|page:1|type:25","luicode":"","fid":"106003type=25&t=3&disable_hot=1&filter_type=realtimehot","lfid":"","uicode":""},"scheme":"https:\/\/m.weibo.cn\/search?containerid=100103type%3D1%26t%3D10%26q%3D%E6%A0%96%E9%9C%9E%E9%87%91%E7%9F%BF&isnewpage=1&extparam=seat%3D1%26filter_type%3Drealtimehot%26cate%3D0%26pos%3D32%26realpos%3D31%26flag%3D0%26c_type%3D31%26display_time%3D1610961193&luicode=10000011&lfid=106003type%3D25%26t%3D3%26disable_hot%3D1%26filter_type%3Drealtimehot","desc":"\u6816\u971e\u91d1\u77ff","pic":"https:\/\/simg.s.weibo.com\/20170303_img_search_33.png"},{"card_type":4,"desc_extr":326338,"itemid":"hotword","actionlog":{"act_code":554,"ext":"t:31|pos:1_33|cate:10103|c_type:31|page:1|type:25","luicode":"","fid":"106003type=25&t=3&disable_hot=1&filter_type=realtimehot","lfid":"","uicode":""},"scheme":"https:\/\/m.weibo.cn\/search?containerid=100103type%3D1%26t%3D10%26q%3D%23%E5%AD%9C%E7%84%B6%E7%83%A4%E5%B7%9D%E7%B2%89%23&isnewpage=1&extparam=seat%3D1%26filter_type%3Drealtimehot%26cate%3D0%26pos%3D33%26realpos%3D32%26flag%3D0%26c_type%3D31%26display_time%3D1610961193&luicode=10000011&lfid=106003type%3D25%26t%3D3%26disable_hot%3D1%26filter_type%3Drealtimehot","desc":"\u5b5c\u7136\u70e4\u5ddd\u7c89","pic":"https:\/\/simg.s.weibo.com\/20170303_img_search_34.png"},{"actionlog":{"act_code":554,"ext":"t:31|pos:1_34|cate:10103|c_type:31|page:1|type:25","luicode":"","fid":"106003type=25&t=3&disable_hot=1&filter_type=realtimehot","lfid":"","uicode":""},"itemid":"hotword","icon":"https:\/\/simg.s.weibo.com\/20200928_new.png","desc_extr":325589,"card_type":4,"scheme":"https:\/\/m.weibo.cn\/search?containerid=100103type%3D1%26t%3D10%26q%3D%E4%B8%AD%E6%96%B9%E5%86%B3%E5%AE%9A%E5%AF%B9%E7%BE%8E%E5%AF%B9%E7%AD%89%E5%88%B6%E8%A3%81&isnewpage=1&extparam=seat%3D1%26filter_type%3Drealtimehot%26cate%3D0%26pos%3D34%26realpos%3D33%26flag%3D1%26c_type%3D31%26display_time%3D1610961193&luicode=10000011&lfid=106003type%3D25%26t%3D3%26disable_hot%3D1%26filter_type%3Drealtimehot","desc":"\u4e2d\u65b9\u51b3\u5b9a\u5bf9\u7f8e\u5bf9\u7b49\u5236\u88c1","pic":"https:\/\/simg.s.weibo.com\/20170303_img_search_35.png"},{"card_type":4,"desc_extr":325422,"itemid":"hotword","actionlog":{"act_code":554,"ext":"t:31|pos:1_35|cate:10103|c_type:31|page:1|type:25","luicode":"","fid":"106003type=25&t=3&disable_hot=1&filter_type=realtimehot","lfid":"","uicode":""},"scheme":"https:\/\/m.weibo.cn\/search?containerid=100103type%3D1%26t%3D10%26q%3D%E8%AE%B8%E5%9E%9A&isnewpage=1&extparam=seat%3D1%26filter_type%3Drealtimehot%26cate%3D0%26pos%3D35%26realpos%3D34%26flag%3D0%26c_type%3D31%26display_time%3D1610961193&luicode=10000011&lfid=106003type%3D25%26t%3D3%26disable_hot%3D1%26filter_type%3Drealtimehot","desc":"\u8bb8\u579a","pic":"https:\/\/simg.s.weibo.com\/20170303_img_search_36.png"},{"actionlog":{"act_code":554,"ext":"t:31|pos:1_36|cate:10103|c_type:31|page:1|type:25","luicode":"","fid":"106003type=25&t=3&disable_hot=1&filter_type=realtimehot","lfid":"","uicode":""},"itemid":"hotword","icon":"https:\/\/simg.s.weibo.com\/20200928_new.png","desc_extr":302484,"card_type":4,"scheme":"https:\/\/m.weibo.cn\/search?containerid=100103type%3D1%26t%3D10%26q%3D%23%E7%8B%BC%E6%AE%BF%E4%B8%8B%E6%94%B6%E5%AE%98%E6%88%98%E6%8A%A5%23&isnewpage=1&extparam=seat%3D1%26filter_type%3Drealtimehot%26cate%3D0%26pos%3D36%26realpos%3D35%26flag%3D1%26c_type%3D31%26display_time%3D1610961193&luicode=10000011&lfid=106003type%3D25%26t%3D3%26disable_hot%3D1%26filter_type%3Drealtimehot","desc":"\u72fc\u6bbf\u4e0b\u6536\u5b98\u6218\u62a5","pic":"https:\/\/simg.s.weibo.com\/20170303_img_search_37.png"},{"actionlog":{"act_code":554,"ext":"t:31|pos:1_37|cate:10103|c_type:31|page:1|type:25","luicode":"","fid":"106003type=25&t=3&disable_hot=1&filter_type=realtimehot","lfid":"","uicode":""},"itemid":"hotword","icon":"https:\/\/simg.s.weibo.com\/20200928_new.png","desc_extr":289818,"card_type":4,"scheme":"https:\/\/m.weibo.cn\/search?containerid=100103type%3D1%26t%3D10%26q%3D%23%E9%BA%BB%E8%BE%A3%E7%81%AB%E9%94%85%E5%BA%95%E6%96%99%E7%84%96%E9%A5%AD%23&isnewpage=1&extparam=seat%3D1%26filter_type%3Drealtimehot%26cate%3D0%26pos%3D37%26realpos%3D36%26flag%3D1%26c_type%3D31%26display_time%3D1610961193&luicode=10000011&lfid=106003type%3D25%26t%3D3%26disable_hot%3D1%26filter_type%3Drealtimehot","desc":"\u9ebb\u8fa3\u706b\u9505\u5e95\u6599\u7116\u996d","pic":"https:\/\/simg.s.weibo.com\/20170303_img_search_38.png"},{"actionlog":{"act_code":554,"ext":"t:31|pos:1_38|cate:10103|c_type:31|page:1|type:25","luicode":"","fid":"106003type=25&t=3&disable_hot=1&filter_type=realtimehot","lfid":"","uicode":""},"itemid":"hotword","icon":"https:\/\/simg.s.weibo.com\/20200928_new.png","desc_extr":285774,"card_type":4,"scheme":"https:\/\/m.weibo.cn\/search?containerid=100103type%3D1%26t%3D10%26q%3D%E5%B9%BC%E5%84%BF%E5%9B%AD3%E5%B2%81%E5%A5%B3%E7%AB%A5%E8%BA%AB%E4%B8%8A%E7%8E%B029%E5%A4%84%E9%92%88%E7%9C%BC&isnewpage=1&extparam=seat%3D1%26filter_type%3Drealtimehot%26cate%3D0%26pos%3D38%26realpos%3D37%26flag%3D1%26c_type%3D31%26display_time%3D1610961193&luicode=10000011&lfid=106003type%3D25%26t%3D3%26disable_hot%3D1%26filter_type%3Drealtimehot","desc":"\u5e7c\u513f\u56ed3\u5c81\u5973\u7ae5\u8eab\u4e0a\u73b029\u5904\u9488\u773c","pic":"https:\/\/simg.s.weibo.com\/20170303_img_search_39.png"},{"card_type":4,"desc_extr":281947,"itemid":"hotword","actionlog":{"act_code":554,"ext":"t:31|pos:1_39|cate:10103|c_type:31|page:1|type:25","luicode":"","fid":"106003type=25&t=3&disable_hot=1&filter_type=realtimehot","lfid":"","uicode":""},"scheme":"https:\/\/m.weibo.cn\/search?containerid=100103type%3D1%26t%3D10%26q%3D%23%E6%B5%81%E5%85%A5%E5%A4%A9%E6%B4%A5%E6%B6%89%E7%96%AB%E9%9B%AA%E7%B3%95%E4%BB%8D%E6%9C%8921%E7%9B%92%E5%9C%A8%E8%BF%BD%E6%9F%A5%23&isnewpage=1&extparam=seat%3D1%26filter_type%3Drealtimehot%26cate%3D0%26pos%3D39%26realpos%3D38%26flag%3D0%26c_type%3D31%26display_time%3D1610961193&luicode=10000011&lfid=106003type%3D25%26t%3D3%26disable_hot%3D1%26filter_type%3Drealtimehot","desc":"\u6d41\u5165\u5929\u6d25\u6d89\u75ab\u96ea\u7cd5\u4ecd\u670921\u76d2\u5728\u8ffd\u67e5","pic":"https:\/\/simg.s.weibo.com\/20170303_img_search_40.png"},{"card_type":4,"desc_extr":281748,"itemid":"hotword","actionlog":{"act_code":554,"ext":"t:31|pos:1_40|cate:10103|c_type:31|page:1|type:25","luicode":"","fid":"106003type=25&t=3&disable_hot=1&filter_type=realtimehot","lfid":"","uicode":""},"scheme":"https:\/\/m.weibo.cn\/search?containerid=100103type%3D1%26t%3D10%26q%3D%23%E6%88%91%E5%B0%B1%E6%98%AF%E8%BF%99%E8%88%AC%E5%A5%B3%E5%AD%90%E5%BC%80%E6%92%AD%23&isnewpage=1&extparam=seat%3D1%26filter_type%3Drealtimehot%26cate%3D0%26pos%3D40%26realpos%3D39%26flag%3D0%26c_type%3D31%26display_time%3D1610961193&luicode=10000011&lfid=106003type%3D25%26t%3D3%26disable_hot%3D1%26filter_type%3Drealtimehot","desc":"\u6211\u5c31\u662f\u8fd9\u822c\u5973\u5b50\u5f00\u64ad","pic":"https:\/\/simg.s.weibo.com\/20170303_img_search_41.png"},{"actionlog":{"act_code":554,"ext":"t:31|pos:1_41|cate:10103|c_type:31|page:1|type:25","luicode":"","fid":"106003type=25&t=3&disable_hot=1&filter_type=realtimehot","lfid":"","uicode":""},"itemid":"hotword","icon":"https:\/\/simg.s.weibo.com\/20200928_new.png","desc_extr":271138,"card_type":4,"scheme":"https:\/\/m.weibo.cn\/search?containerid=100103type%3D1%26t%3D10%26q%3D%23%E5%B9%B4%E8%BD%BB%E4%BA%BA%E5%B0%B1%E5%9C%B0%E8%BF%87%E5%B9%B4%E7%9A%84%E4%BB%AA%E5%BC%8F%E6%84%9F%23&isnewpage=1&extparam=seat%3D1%26filter_type%3Drealtimehot%26cate%3D0%26pos%3D41%26realpos%3D40%26flag%3D1%26c_type%3D31%26display_time%3D1610961193&luicode=10000011&lfid=106003type%3D25%26t%3D3%26disable_hot%3D1%26filter_type%3Drealtimehot","desc":"\u5e74\u8f7b\u4eba\u5c31\u5730\u8fc7\u5e74\u7684\u4eea\u5f0f\u611f","pic":"https:\/\/simg.s.weibo.com\/20170303_img_search_42.png"},{"card_type":4,"desc_extr":271100,"itemid":"hotword","actionlog":{"act_code":554,"ext":"t:31|pos:1_42|cate:10103|c_type:31|page:1|type:25","luicode":"","fid":"106003type=25&t=3&disable_hot=1&filter_type=realtimehot","lfid":"","uicode":""},"scheme":"https:\/\/m.weibo.cn\/search?containerid=100103type%3D1%26t%3D10%26q%3D%23%E7%8C%AB%E5%92%AA%E5%88%B0%E5%BA%95%E8%83%BD%E6%9C%89%E5%A4%9A%E7%B2%98%E4%BA%BA%23&isnewpage=1&extparam=seat%3D1%26filter_type%3Drealtimehot%26cate%3D0%26pos%3D42%26realpos%3D41%26flag%3D0%26c_type%3D31%26display_time%3D1610961193&luicode=10000011&lfid=106003type%3D25%26t%3D3%26disable_hot%3D1%26filter_type%3Drealtimehot","desc":"\u732b\u54aa\u5230\u5e95\u80fd\u6709\u591a\u7c98\u4eba","pic":"https:\/\/simg.s.weibo.com\/20170303_img_search_43.png"},{"actionlog":{"act_code":554,"ext":"t:31|pos:1_43|cate:10103|c_type:31|page:1|type:25","luicode":"","fid":"106003type=25&t=3&disable_hot=1&filter_type=realtimehot","lfid":"","uicode":""},"itemid":"hotword","icon":"https:\/\/simg.s.weibo.com\/20200928_new.png","desc_extr":261401,"card_type":4,"scheme":"https:\/\/m.weibo.cn\/search?containerid=100103type%3D1%26t%3D10%26q%3D%23%E8%93%AC%E4%BD%A9%E5%A5%A5%E4%B8%A4%E5%A4%A9%E7%8B%82%E5%8F%9130%E5%A4%9A%E6%9D%A1%E6%8E%A8%E7%89%B9%E6%94%BB%E5%87%BB%E4%B8%AD%E5%9B%BD%23&isnewpage=1&extparam=seat%3D1%26filter_type%3Drealtimehot%26cate%3D0%26pos%3D43%26realpos%3D42%26flag%3D1%26c_type%3D31%26display_time%3D1610961193&luicode=10000011&lfid=106003type%3D25%26t%3D3%26disable_hot%3D1%26filter_type%3Drealtimehot","desc":"\u84ec\u4f69\u5965\u4e24\u5929\u72c2\u53d130\u591a\u6761\u63a8\u7279\u653b\u51fb\u4e2d\u56fd","pic":"https:\/\/simg.s.weibo.com\/20170303_img_search_44.png"},{"card_type":4,"desc_extr":261203,"itemid":"hotword","actionlog":{"act_code":554,"ext":"t:31|pos:1_44|cate:10103|c_type:31|page:1|type:25","luicode":"","fid":"106003type=25&t=3&disable_hot=1&filter_type=realtimehot","lfid":"","uicode":""},"scheme":"https:\/\/m.weibo.cn\/search?containerid=100103type%3D1%26t%3D10%26q%3D%23%E7%BB%93%E5%A9%9A%E6%98%AF%E4%B8%BA%E4%BA%86%E4%BB%80%E4%B9%88%E5%91%A2%23&isnewpage=1&extparam=seat%3D1%26filter_type%3Drealtimehot%26cate%3D0%26pos%3D44%26realpos%3D43%26flag%3D0%26c_type%3D31%26display_time%3D1610961193&luicode=10000011&lfid=106003type%3D25%26t%3D3%26disable_hot%3D1%26filter_type%3Drealtimehot","desc":"\u7ed3\u5a5a\u662f\u4e3a\u4e86\u4ec0\u4e48\u5462","pic":"https:\/\/simg.s.weibo.com\/20170303_img_search_45.png"},{"actionlog":{"act_code":554,"ext":"t:31|pos:1_45|cate:10103|c_type:31|page:1|type:25","luicode":"","fid":"106003type=25&t=3&disable_hot=1&filter_type=realtimehot","lfid":"","uicode":""},"itemid":"hotword","icon":"https:\/\/simg.s.weibo.com\/20200928_new.png","desc_extr":261062,"card_type":4,"scheme":"https:\/\/m.weibo.cn\/search?containerid=100103type%3D1%26t%3D10%26q%3DPrada%E7%9A%84%E7%9C%BC%E6%B3%AAPradaPrada%E7%9A%84%E6%8E%89&isnewpage=1&extparam=seat%3D1%26filter_type%3Drealtimehot%26cate%3D0%26pos%3D45%26realpos%3D44%26flag%3D1%26c_type%3D31%26display_time%3D1610961193&luicode=10000011&lfid=106003type%3D25%26t%3D3%26disable_hot%3D1%26filter_type%3Drealtimehot","desc":"Prada\u7684\u773c\u6ceaPradaPrada\u7684\u6389","pic":"https:\/\/simg.s.weibo.com\/20170303_img_search_46.png"},{"card_type":4,"desc_extr":260122,"itemid":"hotword","actionlog":{"act_code":554,"ext":"t:31|pos:1_46|cate:10103|c_type:31|page:1|type:25","luicode":"","fid":"106003type=25&t=3&disable_hot=1&filter_type=realtimehot","lfid":"","uicode":""},"scheme":"https:\/\/m.weibo.cn\/search?containerid=100103type%3D1%26t%3D10%26q%3D%E5%8D%8A%E5%AF%BC%E4%BD%93&isnewpage=1&extparam=seat%3D1%26filter_type%3Drealtimehot%26cate%3D0%26pos%3D46%26realpos%3D45%26flag%3D0%26c_type%3D31%26display_time%3D1610961193&luicode=10000011&lfid=106003type%3D25%26t%3D3%26disable_hot%3D1%26filter_type%3Drealtimehot","desc":"\u534a\u5bfc\u4f53","pic":"https:\/\/simg.s.weibo.com\/20170303_img_search_47.png"},{"card_type":4,"desc_extr":259809,"itemid":"hotword","actionlog":{"act_code":554,"ext":"t:31|pos:1_47|cate:10103|c_type:31|page:1|type:25","luicode":"","fid":"106003type=25&t=3&disable_hot=1&filter_type=realtimehot","lfid":"","uicode":""},"scheme":"https:\/\/m.weibo.cn\/search?containerid=100103type%3D1%26t%3D10%26q%3D%23%E6%9C%AA%E5%8F%82%E5%8A%A0%E5%90%8C%E4%BA%8B%E7%94%9F%E6%97%A5%E5%AE%B4%E8%A2%AB%E7%BD%9A%E5%BD%93%E4%BA%8B%E7%BB%8F%E7%90%86%E5%8F%91%E5%A3%B0%23&isnewpage=1&extparam=seat%3D1%26filter_type%3Drealtimehot%26cate%3D0%26pos%3D47%26realpos%3D46%26flag%3D0%26c_type%3D31%26display_time%3D1610961193&luicode=10000011&lfid=106003type%3D25%26t%3D3%26disable_hot%3D1%26filter_type%3Drealtimehot","desc":"\u672a\u53c2\u52a0\u540c\u4e8b\u751f\u65e5\u5bb4\u88ab\u7f5a\u5f53\u4e8b\u7ecf\u7406\u53d1\u58f0","pic":"https:\/\/simg.s.weibo.com\/20170303_img_search_48.png"},{"card_type":4,"desc_extr":259356,"itemid":"hotword","actionlog":{"act_code":554,"ext":"t:31|pos:1_48|cate:10103|c_type:31|page:1|type:25","luicode":"","fid":"106003type=25&t=3&disable_hot=1&filter_type=realtimehot","lfid":"","uicode":""},"scheme":"https:\/\/m.weibo.cn\/search?containerid=100103type%3D1%26t%3D10%26q%3D%E7%BE%8E%E5%AA%92%E5%86%8D%E6%9B%9D%E5%9B%BD%E4%BC%9A%E9%AA%9A%E4%B9%B1%E7%BB%86%E8%8A%82&isnewpage=1&extparam=seat%3D1%26filter_type%3Drealtimehot%26cate%3D0%26pos%3D48%26realpos%3D47%26flag%3D0%26c_type%3D31%26display_time%3D1610961193&luicode=10000011&lfid=106003type%3D25%26t%3D3%26disable_hot%3D1%26filter_type%3Drealtimehot","desc":"\u7f8e\u5a92\u518d\u66dd\u56fd\u4f1a\u9a9a\u4e71\u7ec6\u8282","pic":"https:\/\/simg.s.weibo.com\/20170303_img_search_49.png"},{"actionlog":{"act_code":554,"ext":"t:31|pos:1_49|cate:10103|c_type:31|page:1|type:25","luicode":"","fid":"106003type=25&t=3&disable_hot=1&filter_type=realtimehot","lfid":"","uicode":""},"itemid":"hotword","icon":"https:\/\/simg.s.weibo.com\/20200928_new.png","desc_extr":258436,"card_type":4,"scheme":"https:\/\/m.weibo.cn\/search?containerid=100103type%3D1%26t%3D10%26q%3D%E4%BB%A3%E5%AD%95&isnewpage=1&extparam=seat%3D1%26filter_type%3Drealtimehot%26cate%3D0%26pos%3D49%26realpos%3D48%26flag%3D1%26c_type%3D31%26display_time%3D1610961193&luicode=10000011&lfid=106003type%3D25%26t%3D3%26disable_hot%3D1%26filter_type%3Drealtimehot","desc":"\u4ee3\u5b55","pic":"https:\/\/simg.s.weibo.com\/20170303_img_search_50.png"}]},{"show_type":0,"title":"\u5b9e\u65f6\u4e0a\u5347\u70ed\u70b9","card_type":11,"card_group":[{"card_type":4,"desc_extr":131598,"itemid":"realtimehotspotcon","actionlog":{"act_code":554,"ext":"t:25|c_type:25|pos:1_1|cate:10103|prop:0|page:1|type:25","luicode":"","fid":"106003type=25&t=3&disable_hot=1&filter_type=realtimehot","lfid":"","uicode":""},"scheme":"https:\/\/m.weibo.cn\/search?containerid=100103type%3D1%26t%3D10%26q%3D%E8%8C%83%E6%B9%89%E6%B9%89+%E5%9B%9B%E5%8D%81is+fabulous&isnewpage=1&extparam=seat%3D1%26c_type%3D25%26pos%3D0%26q%3D%25E8%258C%2583%25E6%25B9%2589%25E6%25B9%2589%2520%25E5%259B%259B%25E5%258D%2581is%2520fabulous%26mi_cid%3D100103%26filter_type%3Dpersonal%26cate%3D%26display_time%3D1610961193&luicode=10000011&lfid=106003type%3D25%26t%3D3%26disable_hot%3D1%26filter_type%3Drealtimehot","desc":"\u8303\u6e49\u6e49 \u56db\u5341is fabulous","pic":"https:\/\/simg.s.weibo.com\/20170306_plus_new1.png"},{"actionlog":{"act_code":554,"ext":"t:25|c_type:25|pos:1_2|cate:10103|prop:0|page:1|type:25","luicode":"","fid":"106003type=25&t=3&disable_hot=1&filter_type=realtimehot","lfid":"","uicode":""},"itemid":"realtimehotspotcon","icon":"https:\/\/simg.s.weibo.com\/20200928_plus.png","desc_extr":10675,"card_type":4,"scheme":"https:\/\/m.weibo.cn\/search?containerid=100103type%3D1%26t%3D10%26q%3D%232%E4%BE%8B%E6%97%A0%E7%97%87%E7%8A%B6%E6%9B%BE%E4%B9%98Z216%E6%AC%A1%E5%92%8CK262%E6%AC%A1%E5%88%97%E8%BD%A6%23&isnewpage=1&extparam=seat%3D1%26c_type%3D25%26pos%3D1%26q%3D%25232%25E4%25BE%258B%25E6%2597%25A0%25E7%2597%2587%25E7%258A%25B6%25E6%259B%25BE%25E4%25B9%2598Z216%25E6%25AC%25A1%25E5%2592%258CK262%25E6%25AC%25A1%25E5%2588%2597%25E8%25BD%25A6%2523%26mi_cid%3D100103%26filter_type%3Dpersonal%26cate%3D%26display_time%3D1610961193&luicode=10000011&lfid=106003type%3D25%26t%3D3%26disable_hot%3D1%26filter_type%3Drealtimehot","desc":"2\u4f8b\u65e0\u75c7\u72b6\u66fe\u4e58Z216\u6b21\u548cK262\u6b21\u5217\u8f66","pic":"https:\/\/simg.s.weibo.com\/20170306_plus_new1.png"},{"card_type":4,"desc_extr":63110,"itemid":"realtimehotspotcon","actionlog":{"act_code":554,"ext":"t:25|c_type:25|pos:1_3|cate:10103|prop:0|page:1|type:25","luicode":"","fid":"106003type=25&t=3&disable_hot=1&filter_type=realtimehot","lfid":"","uicode":""},"scheme":"https:\/\/m.weibo.cn\/search?containerid=100103type%3D1%26t%3D10%26q%3D%23%E9%A9%AC%E5%98%89%E7%A5%BA%E9%97%AE%E5%90%B4%E5%BD%A4%E5%96%9C%E6%AC%A2%E6%BC%94%E5%91%98%E8%BF%98%E6%98%AF%E7%8E%8B%E7%89%8C%23&isnewpage=1&extparam=seat%3D1%26c_type%3D25%26pos%3D2%26q%3D%2523%25E9%25A9%25AC%25E5%2598%2589%25E7%25A5%25BA%25E9%2597%25AE%25E5%2590%25B4%25E5%25BD%25A4%25E5%2596%259C%25E6%25AC%25A2%25E6%25BC%2594%25E5%2591%2598%25E8%25BF%2598%25E6%2598%25AF%25E7%258E%258B%25E7%2589%258C%2523%26mi_cid%3D100103%26filter_type%3Dpersonal%26cate%3D%26display_time%3D1610961193&luicode=10000011&lfid=106003type%3D25%26t%3D3%26disable_hot%3D1%26filter_type%3Drealtimehot","desc":"\u9a6c\u5609\u797a\u95ee\u5434\u5f64\u559c\u6b22\u6f14\u5458\u8fd8\u662f\u738b\u724c","pic":"https:\/\/simg.s.weibo.com\/20170306_plus_new1.png"},{"actionlog":{"act_code":554,"ext":"t:25|c_type:25|pos:1_4|cate:10103|prop:0|page:1|type:25","luicode":"","fid":"106003type=25&t=3&disable_hot=1&filter_type=realtimehot","lfid":"","uicode":""},"itemid":"realtimehotspotcon","icon":"https:\/\/simg.s.weibo.com\/20200928_plus.png","desc_extr":15044,"card_type":4,"scheme":"https:\/\/m.weibo.cn\/search?containerid=100103type%3D1%26t%3D10%26q%3D%23%E8%9C%9C%E6%B1%81%E7%BA%A2%E7%83%A7%E9%B9%8C%E9%B9%91%E8%9B%8B%23&isnewpage=1&extparam=seat%3D1%26c_type%3D25%26pos%3D3%26q%3D%2523%25E8%259C%259C%25E6%25B1%2581%25E7%25BA%25A2%25E7%2583%25A7%25E9%25B9%258C%25E9%25B9%2591%25E8%259B%258B%2523%26mi_cid%3D100103%26filter_type%3Dpersonal%26cate%3D%26display_time%3D1610961193&luicode=10000011&lfid=106003type%3D25%26t%3D3%26disable_hot%3D1%26filter_type%3Drealtimehot","desc":"\u871c\u6c41\u7ea2\u70e7\u9e4c\u9e51\u86cb","pic":"https:\/\/simg.s.weibo.com\/20170306_plus_new1.png"},{"actionlog":{"act_code":554,"ext":"t:25|c_type:25|pos:1_5|cate:10103|prop:0|page:1|type:25","luicode":"","fid":"106003type=25&t=3&disable_hot=1&filter_type=realtimehot","lfid":"","uicode":""},"itemid":"realtimehotspotcon","icon":"https:\/\/simg.s.weibo.com\/20200928_plus.png","desc_extr":11149,"card_type":4,"scheme":"https:\/\/m.weibo.cn\/search?containerid=100103type%3D1%26t%3D10%26q%3D8%E6%97%AC%E7%88%B7%E7%88%B7%E5%87%8C%E6%99%A8%E8%B5%A4%E8%86%8A%E8%B7%9110%E5%85%AC%E9%87%8C&isnewpage=1&extparam=seat%3D1%26c_type%3D25%26pos%3D4%26q%3D8%25E6%2597%25AC%25E7%2588%25B7%25E7%2588%25B7%25E5%2587%258C%25E6%2599%25A8%25E8%25B5%25A4%25E8%2586%258A%25E8%25B7%259110%25E5%2585%25AC%25E9%2587%258C%26mi_cid%3D100103%26filter_type%3Dpersonal%26cate%3D%26display_time%3D1610961193&luicode=10000011&lfid=106003type%3D25%26t%3D3%26disable_hot%3D1%26filter_type%3Drealtimehot","desc":"8\u65ec\u7237\u7237\u51cc\u6668\u8d64\u818a\u8dd110\u516c\u91cc","pic":"https:\/\/simg.s.weibo.com\/20170306_plus_new1.png"},{"card_type":4,"desc_extr":33377,"itemid":"realtimehotspotcon","actionlog":{"act_code":554,"ext":"t:25|c_type:25|pos:1_6|cate:10103|prop:0|page:1|type:25","luicode":"","fid":"106003type=25&t=3&disable_hot=1&filter_type=realtimehot","lfid":"","uicode":""},"scheme":"https:\/\/m.weibo.cn\/search?containerid=100103type%3D1%26t%3D10%26q%3D%23%E8%BF%87%E5%B9%B4%E6%91%86%E6%91%8A%E5%9B%BE%E9%89%B4%23&isnewpage=1&extparam=seat%3D1%26c_type%3D25%26pos%3D5%26q%3D%2523%25E8%25BF%2587%25E5%25B9%25B4%25E6%2591%2586%25E6%2591%258A%25E5%259B%25BE%25E9%2589%25B4%2523%26mi_cid%3D100103%26filter_type%3Dpersonal%26cate%3D%26display_time%3D1610961193&luicode=10000011&lfid=106003type%3D25%26t%3D3%26disable_hot%3D1%26filter_type%3Drealtimehot","desc":"\u8fc7\u5e74\u6446\u644a\u56fe\u9274","pic":"https:\/\/simg.s.weibo.com\/20170306_plus_new1.png"},{"card_type":4,"desc_extr":53083,"itemid":"realtimehotspotcon","actionlog":{"act_code":554,"ext":"t:25|c_type:25|pos:1_7|cate:10103|prop:0|page:1|type:25","luicode":"","fid":"106003type=25&t=3&disable_hot=1&filter_type=realtimehot","lfid":"","uicode":""},"scheme":"https:\/\/m.weibo.cn\/search?containerid=100103type%3D1%26t%3D10%26q%3D%23%E6%B1%9F%E8%8B%8F1%E6%89%B9%E6%AC%A1%E6%9C%AA%E9%80%81%E6%A3%80%E8%BF%9B%E5%8F%A3%E5%86%BB%E7%89%9B%E8%82%89%E6%A3%80%E5%87%BA%E9%98%B3%E6%80%A7%23&isnewpage=1&extparam=seat%3D1%26c_type%3D25%26pos%3D6%26q%3D%2523%25E6%25B1%259F%25E8%258B%258F1%25E6%2589%25B9%25E6%25AC%25A1%25E6%259C%25AA%25E9%2580%2581%25E6%25A3%2580%25E8%25BF%259B%25E5%258F%25A3%25E5%2586%25BB%25E7%2589%259B%25E8%2582%2589%25E6%25A3%2580%25E5%2587%25BA%25E9%2598%25B3%25E6%2580%25A7%2523%26mi_cid%3D100103%26filter_type%3Dpersonal%26cate%3D%26display_time%3D1610961193&luicode=10000011&lfid=106003type%3D25%26t%3D3%26disable_hot%3D1%26filter_type%3Drealtimehot","desc":"\u6c5f\u82cf1\u6279\u6b21\u672a\u9001\u68c0\u8fdb\u53e3\u51bb\u725b\u8089\u68c0\u51fa\u9633\u6027","pic":"https:\/\/simg.s.weibo.com\/20170306_plus_new1.png"},{"actionlog":{"act_code":554,"ext":"t:25|c_type:25|pos:1_8|cate:10103|prop:0|page:1|type:25","luicode":"","fid":"106003type=25&t=3&disable_hot=1&filter_type=realtimehot","lfid":"","uicode":""},"itemid":"realtimehotspotcon","icon":"https:\/\/simg.s.weibo.com\/20200928_plus.png","desc_extr":12403,"card_type":4,"scheme":"https:\/\/m.weibo.cn\/search?containerid=100103type%3D1%26t%3D10%26q%3D%E5%B9%BF%E8%A5%BF%E5%8F%91%E6%94%BE%E8%B4%AD%E8%BD%A6%E8%A1%A5%E8%B4%B4&isnewpage=1&extparam=seat%3D1%26c_type%3D25%26pos%3D7%26q%3D%25E5%25B9%25BF%25E8%25A5%25BF%25E5%258F%2591%25E6%2594%25BE%25E8%25B4%25AD%25E8%25BD%25A6%25E8%25A1%25A5%25E8%25B4%25B4%26mi_cid%3D100103%26filter_type%3Dpersonal%26cate%3D%26display_time%3D1610961193&luicode=10000011&lfid=106003type%3D25%26t%3D3%26disable_hot%3D1%26filter_type%3Drealtimehot","desc":"\u5e7f\u897f\u53d1\u653e\u8d2d\u8f66\u8865\u8d34","pic":"https:\/\/simg.s.weibo.com\/20170306_plus_new1.png"},{"card_type":4,"desc_extr":156543,"itemid":"realtimehotspotcon","actionlog":{"act_code":554,"ext":"t:25|c_type:25|pos:1_9|cate:10103|prop:0|page:1|type:25","luicode":"","fid":"106003type=25&t=3&disable_hot=1&filter_type=realtimehot","lfid":"","uicode":""},"scheme":"https:\/\/m.weibo.cn\/search?containerid=100103type%3D1%26t%3D10%26q%3D%E5%AD%9F%E4%BD%B3+%E6%A3%89%E7%9D%A1%E8%A1%A3%E6%B2%A1%E6%9C%89%E8%A2%96%E5%A5%97%E5%B0%B1%E4%B8%8D%E5%AE%8C%E6%95%B4&isnewpage=1&extparam=seat%3D1%26c_type%3D25%26pos%3D8%26q%3D%25E5%25AD%259F%25E4%25BD%25B3%2520%25E6%25A3%2589%25E7%259D%25A1%25E8%25A1%25A3%25E6%25B2%25A1%25E6%259C%2589%25E8%25A2%2596%25E5%25A5%2597%25E5%25B0%25B1%25E4%25B8%258D%25E5%25AE%258C%25E6%2595%25B4%26mi_cid%3D100103%26filter_type%3Dpersonal%26cate%3D%26display_time%3D1610961193&luicode=10000011&lfid=106003type%3D25%26t%3D3%26disable_hot%3D1%26filter_type%3Drealtimehot","desc":"\u5b5f\u4f73 \u68c9\u7761\u8863\u6ca1\u6709\u8896\u5957\u5c31\u4e0d\u5b8c\u6574","pic":"https:\/\/simg.s.weibo.com\/20170306_plus_new1.png"},{"card_type":4,"desc_extr":23436,"itemid":"realtimehotspotcon","actionlog":{"act_code":554,"ext":"t:25|c_type:25|pos:1_10|cate:10103|prop:0|page:1|type:25","luicode":"","fid":"106003type=25&t=3&disable_hot=1&filter_type=realtimehot","lfid":"","uicode":""},"scheme":"https:\/\/m.weibo.cn\/search?containerid=100103type%3D1%26t%3D10%26q%3D%23%E6%96%B0%E7%96%86%E5%BA%93%E6%9C%A8%E5%A1%94%E6%A0%BC%E6%B2%99%E6%BC%A0%E6%B5%B7%E5%B8%82%E8%9C%83%E6%A5%BC%23&isnewpage=1&extparam=seat%3D1%26c_type%3D25%26pos%3D9%26q%3D%2523%25E6%2596%25B0%25E7%2596%2586%25E5%25BA%2593%25E6%259C%25A8%25E5%25A1%2594%25E6%25A0%25BC%25E6%25B2%2599%25E6%25BC%25A0%25E6%25B5%25B7%25E5%25B8%2582%25E8%259C%2583%25E6%25A5%25BC%2523%26mi_cid%3D100103%26filter_type%3Dpersonal%26cate%3D%26display_time%3D1610961193&luicode=10000011&lfid=106003type%3D25%26t%3D3%26disable_hot%3D1%26filter_type%3Drealtimehot","desc":"\u65b0\u7586\u5e93\u6728\u5854\u683c\u6c99\u6f20\u6d77\u5e02\u8703\u697c","pic":"https:\/\/simg.s.weibo.com\/20170306_plus_new1.png"},{"card_type":4,"desc_extr":91625,"itemid":"realtimehotspotcon","actionlog":{"act_code":554,"ext":"t:25|c_type:25|pos:1_11|cate:10103|prop:0|page:1|type:25","luicode":"","fid":"106003type=25&t=3&disable_hot=1&filter_type=realtimehot","lfid":"","uicode":""},"scheme":"https:\/\/m.weibo.cn\/search?containerid=100103type%3D1%26t%3D10%26q%3D%E6%9D%8E%E8%8B%B1%E7%88%B1%E7%8A%B6%E6%80%81&isnewpage=1&extparam=seat%3D1%26c_type%3D25%26pos%3D10%26q%3D%25E6%259D%258E%25E8%258B%25B1%25E7%2588%25B1%25E7%258A%25B6%25E6%2580%2581%26mi_cid%3D100103%26filter_type%3Dpersonal%26cate%3D%26display_time%3D1610961193&luicode=10000011&lfid=106003type%3D25%26t%3D3%26disable_hot%3D1%26filter_type%3Drealtimehot","desc":"\u674e\u82f1\u7231\u72b6\u6001","pic":"https:\/\/simg.s.weibo.com\/20170306_plus_new1.png"},{"actionlog":{"act_code":554,"ext":"t:25|c_type:25|pos:1_12|cate:10103|prop:0|page:1|type:25","luicode":"","fid":"106003type=25&t=3&disable_hot=1&filter_type=realtimehot","lfid":"","uicode":""},"itemid":"realtimehotspotcon","icon":"https:\/\/simg.s.weibo.com\/20200928_plus.png","desc_extr":33885,"card_type":4,"scheme":"https:\/\/m.weibo.cn\/search?containerid=100103type%3D1%26t%3D10%26q%3D%E5%85%B3%E6%99%93%E5%BD%A4%E5%8F%A4%E8%A3%85&isnewpage=1&extparam=seat%3D1%26c_type%3D25%26pos%3D11%26q%3D%25E5%2585%25B3%25E6%2599%2593%25E5%25BD%25A4%25E5%258F%25A4%25E8%25A3%2585%26mi_cid%3D100103%26filter_type%3Dpersonal%26cate%3D%26display_time%3D1610961193&luicode=10000011&lfid=106003type%3D25%26t%3D3%26disable_hot%3D1%26filter_type%3Drealtimehot","desc":"\u5173\u6653\u5f64\u53e4\u88c5","pic":"https:\/\/simg.s.weibo.com\/20170306_plus_new1.png"},{"card_type":4,"desc_extr":34082,"itemid":"realtimehotspotcon","actionlog":{"act_code":554,"ext":"t:25|c_type:25|pos:1_13|cate:10103|prop:0|page:1|type:25","luicode":"","fid":"106003type=25&t=3&disable_hot=1&filter_type=realtimehot","lfid":"","uicode":""},"scheme":"https:\/\/m.weibo.cn\/search?containerid=100103type%3D1%26t%3D10%26q%3D%23%E7%8E%A9%E6%8B%BC%E5%9B%BE%E6%9C%89%E5%A4%9A%E7%83%A7%E8%84%91%23&isnewpage=1&extparam=seat%3D1%26c_type%3D25%26pos%3D12%26q%3D%2523%25E7%258E%25A9%25E6%258B%25BC%25E5%259B%25BE%25E6%259C%2589%25E5%25A4%259A%25E7%2583%25A7%25E8%2584%2591%2523%26mi_cid%3D100103%26filter_type%3Dpersonal%26cate%3D%26display_time%3D1610961193&luicode=10000011&lfid=106003type%3D25%26t%3D3%26disable_hot%3D1%26filter_type%3Drealtimehot","desc":"\u73a9\u62fc\u56fe\u6709\u591a\u70e7\u8111","pic":"https:\/\/simg.s.weibo.com\/20170306_plus_new1.png"},{"card_type":4,"desc_extr":14321,"itemid":"realtimehotspotcon","actionlog":{"act_code":554,"ext":"t:25|c_type:25|pos:1_14|cate:10103|prop:0|page:1|type:25","luicode":"","fid":"106003type=25&t=3&disable_hot=1&filter_type=realtimehot","lfid":"","uicode":""},"scheme":"https:\/\/m.weibo.cn\/search?containerid=100103type%3D1%26t%3D10%26q%3D%23%E9%94%A1%E5%AE%89%E8%B4%9F%E8%A7%92%E5%BA%A6%E6%8B%89%E6%9D%86%23&isnewpage=1&extparam=seat%3D1%26c_type%3D25%26pos%3D13%26q%3D%2523%25E9%2594%25A1%25E5%25AE%2589%25E8%25B4%259F%25E8%25A7%2592%25E5%25BA%25A6%25E6%258B%2589%25E6%259D%2586%2523%26mi_cid%3D100103%26filter_type%3Dpersonal%26cate%3D%26display_time%3D1610961193&luicode=10000011&lfid=106003type%3D25%26t%3D3%26disable_hot%3D1%26filter_type%3Drealtimehot","desc":"\u9521\u5b89\u8d1f\u89d2\u5ea6\u62c9\u6746","pic":"https:\/\/simg.s.weibo.com\/20170306_plus_new1.png"},{"card_type":4,"desc_extr":13946,"itemid":"realtimehotspotcon","actionlog":{"act_code":554,"ext":"t:25|c_type:25|pos:1_15|cate:10103|prop:0|page:1|type:25","luicode":"","fid":"106003type=25&t=3&disable_hot=1&filter_type=realtimehot","lfid":"","uicode":""},"scheme":"https:\/\/m.weibo.cn\/search?containerid=100103type%3D1%26t%3D10%26q%3D%23%E4%B8%AD%E8%81%94%E5%8A%9E%E5%BC%BA%E7%83%88%E8%B0%B4%E8%B4%A3%E7%BE%8E%E5%9B%BD%E5%86%8D%E6%AC%A1%E4%B8%8A%E6%BC%94%E5%88%B6%E8%A3%81%E9%97%B9%E5%89%A7%23&isnewpage=1&extparam=seat%3D1%26c_type%3D25%26pos%3D14%26q%3D%2523%25E4%25B8%25AD%25E8%2581%2594%25E5%258A%259E%25E5%25BC%25BA%25E7%2583%2588%25E8%25B0%25B4%25E8%25B4%25A3%25E7%25BE%258E%25E5%259B%25BD%25E5%2586%258D%25E6%25AC%25A1%25E4%25B8%258A%25E6%25BC%2594%25E5%2588%25B6%25E8%25A3%2581%25E9%2597%25B9%25E5%2589%25A7%2523%26mi_cid%3D100103%26filter_type%3Dpersonal%26cate%3D%26display_time%3D1610961193&luicode=10000011&lfid=106003type%3D25%26t%3D3%26disable_hot%3D1%26filter_type%3Drealtimehot","desc":"\u4e2d\u8054\u529e\u5f3a\u70c8\u8c34\u8d23\u7f8e\u56fd\u518d\u6b21\u4e0a\u6f14\u5236\u88c1\u95f9\u5267","pic":"https:\/\/simg.s.weibo.com\/20170306_plus_new1.png"},{"card_type":4,"desc_extr":104800,"itemid":"realtimehotspotcon","actionlog":{"act_code":554,"ext":"t:25|c_type:25|pos:1_16|cate:10103|prop:0|page:1|type:25","luicode":"","fid":"106003type=25&t=3&disable_hot=1&filter_type=realtimehot","lfid":"","uicode":""},"scheme":"https:\/\/m.weibo.cn\/search?containerid=100103type%3D1%26t%3D10%26q%3D%23%E5%82%BB%E7%8B%8D%E5%AD%90%E7%9A%84%E5%8F%AF%E7%88%B1%E6%98%AF%E7%94%A8%E8%84%91%E5%AD%90%E6%8D%A2%E7%9A%84%23&isnewpage=1&extparam=seat%3D1%26c_type%3D25%26pos%3D15%26q%3D%2523%25E5%2582%25BB%25E7%258B%258D%25E5%25AD%2590%25E7%259A%2584%25E5%258F%25AF%25E7%2588%25B1%25E6%2598%25AF%25E7%2594%25A8%25E8%2584%2591%25E5%25AD%2590%25E6%258D%25A2%25E7%259A%2584%2523%26mi_cid%3D100103%26filter_type%3Dpersonal%26cate%3D%26display_time%3D1610961193&luicode=10000011&lfid=106003type%3D25%26t%3D3%26disable_hot%3D1%26filter_type%3Drealtimehot","desc":"\u50bb\u72cd\u5b50\u7684\u53ef\u7231\u662f\u7528\u8111\u5b50\u6362\u7684","pic":"https:\/\/simg.s.weibo.com\/20170306_plus_new1.png"}]},{"show_type":0,"title":"\u5a31\u4e50\u6700\u65b0\u52a8\u6001","card_type":11,"card_group":[{"time_interval":3,"still_dict":[],"direction":0,"card_type":120,"subcard_type":25,"groups":[{"card_type":25,"pic":"https:\/\/simg.s.weibo.com\/20201204_entertainment_ranking_1.png","display_arrow":0,"card_display_type":1,"actionlog":{"act_code":554,"ext":"t:157|pos:1_0|cate:5023|c_type:157|page:1|type:25","luicode":"","fid":"106003type=25&t=3&disable_hot=1&filter_type=realtimehot","lfid":"","uicode":""},"scheme":"sinaweibo:\/\/pageinfo?containerid=106003type%3d25%26t%3d3%26disable_hot%3d1%26filter_type%3dfun&extparam=fun_more%3D1","desc":"\u5708\u5185\u70ed\u5ea619883 | \u51fa\u5708\u6307\u657013.4%","title_sub":"\u5b5f\u4f73 \u68c9\u7761\u8863\u6ca1\u6709\u8896\u5957\u5c31\u4e0d\u5b8c\u6574"},{"display_arrow":0,"card_display_type":1,"actionlog":{"act_code":554,"ext":"t:157|pos:1_1|cate:5023|c_type:157|page:1|type:25","luicode":"","fid":"106003type=25&t=3&disable_hot=1&filter_type=realtimehot","lfid":"","uicode":""},"title_flag_pic":"https:\/\/simg.s.weibo.com\/20201204_plus.png","pic":"https:\/\/simg.s.weibo.com\/20201204_entertainment_ranking_2.png","card_type":25,"scheme":"sinaweibo:\/\/pageinfo?containerid=106003type%3d25%26t%3d3%26disable_hot%3d1%26filter_type%3dfun&extparam=fun_more%3D1","desc":"\u5708\u5185\u70ed\u5ea617260 | \u51fa\u5708\u6307\u657019.7%","title_sub":"\u8303\u6e49\u6e49 \u56db\u5341is fabulous"},{"display_arrow":0,"card_display_type":1,"actionlog":{"act_code":554,"ext":"t:157|pos:1_2|cate:5023|c_type:157|page:1|type:25","luicode":"","fid":"106003type=25&t=3&disable_hot=1&filter_type=realtimehot","lfid":"","uicode":""},"title_flag_pic":"https:\/\/simg.s.weibo.com\/20200917_new.png","pic":"https:\/\/simg.s.weibo.com\/20201204_entertainment_ranking_3.png","card_type":25,"scheme":"sinaweibo:\/\/pageinfo?containerid=106003type%3d25%26t%3d3%26disable_hot%3d1%26filter_type%3dfun&extparam=fun_more%3D1","desc":"\u5708\u5185\u70ed\u5ea68510 | \u51fa\u5708\u6307\u657015.8%","title_sub":"\u5173\u6653\u5f64\u53e4\u88c5"},{"card_type":25,"pic":"https:\/\/simg.s.weibo.com\/20201204_entertainment_ranking_4.png","display_arrow":0,"card_display_type":1,"actionlog":{"act_code":554,"ext":"t:157|pos:1_3|cate:5023|c_type:157|page:1|type:25","luicode":"","fid":"106003type=25&t=3&disable_hot=1&filter_type=realtimehot","lfid":"","uicode":""},"scheme":"sinaweibo:\/\/pageinfo?containerid=106003type%3d25%26t%3d3%26disable_hot%3d1%26filter_type%3dfun&extparam=fun_more%3D1","desc":"\u5708\u5185\u70ed\u5ea67684 | \u51fa\u5708\u6307\u65703.7%","title_sub":"\u5370\u5c0f\u5929\u5728\u6c88\u9633\u7ad9\u7ad9\u8df3\u963f\u91cc\u5df4\u5df4"},{"card_type":25,"pic":"https:\/\/simg.s.weibo.com\/20201204_entertainment_ranking_5.png","display_arrow":0,"card_display_type":1,"actionlog":{"act_code":554,"ext":"t:157|pos:1_4|cate:5023|c_type:157|page:1|type:25","luicode":"","fid":"106003type=25&t=3&disable_hot=1&filter_type=realtimehot","lfid":"","uicode":""},"scheme":"sinaweibo:\/\/pageinfo?containerid=106003type%3d25%26t%3d3%26disable_hot%3d1%26filter_type%3dfun&extparam=fun_more%3D1","desc":"\u5708\u5185\u70ed\u5ea66956 | \u51fa\u5708\u6307\u657010.3%","title_sub":"\u9a6c\u5609\u797a\u95ee\u5434\u5f64\u559c\u6b22\u6f14\u5458\u8fd8\u662f\u738b\u724c"},{"card_type":25,"pic":"https:\/\/simg.s.weibo.com\/20201204_entertainment_ranking_6.png","display_arrow":0,"card_display_type":1,"actionlog":{"act_code":554,"ext":"t:157|pos:1_5|cate:5023|c_type:157|page:1|type:25","luicode":"","fid":"106003type=25&t=3&disable_hot=1&filter_type=realtimehot","lfid":"","uicode":""},"scheme":"sinaweibo:\/\/pageinfo?containerid=106003type%3d25%26t%3d3%26disable_hot%3d1%26filter_type%3dfun&extparam=fun_more%3D1","desc":"\u5708\u5185\u70ed\u5ea66361 | \u51fa\u5708\u6307\u65702.4%","title_sub":"\u6731\u6b63\u5ef7\u70b9\u540d\u70b9\u59d3\u5f0f\u56de\u5e94\u7eef\u95fb"},{"card_type":25,"pic":"https:\/\/simg.s.weibo.com\/20201204_entertainment_ranking_7.png","display_arrow":0,"card_display_type":1,"actionlog":{"act_code":554,"ext":"t:157|pos:1_6|cate:5023|c_type:157|page:1|type:25","luicode":"","fid":"106003type=25&t=3&disable_hot=1&filter_type=realtimehot","lfid":"","uicode":""},"scheme":"sinaweibo:\/\/pageinfo?containerid=106003type%3d25%26t%3d3%26disable_hot%3d1%26filter_type%3dfun&extparam=fun_more%3D1","desc":"\u5708\u5185\u70ed\u5ea66352 | \u51fa\u5708\u6307\u65705.3%","title_sub":"\u8d75\u8ba9\u8bb2\u8ff0\u9009\u79c0\u5fc3\u8def"},{"display_arrow":0,"card_display_type":1,"actionlog":{"act_code":554,"ext":"t:157|pos:1_7|cate:5023|c_type:157|page:1|type:25","luicode":"","fid":"106003type=25&t=3&disable_hot=1&filter_type=realtimehot","lfid":"","uicode":""},"title_flag_pic":"https:\/\/simg.s.weibo.com\/20201222_reduce_small1.png","pic":"https:\/\/simg.s.weibo.com\/20201204_entertainment_ranking_8.png","card_type":25,"scheme":"sinaweibo:\/\/pageinfo?containerid=106003type%3d25%26t%3d3%26disable_hot%3d1%26filter_type%3dfun&extparam=fun_more%3D1","desc":"\u5708\u5185\u70ed\u5ea66301 | \u51fa\u5708\u6307\u65707.7%","title_sub":"\u59da\u5b89\u5a1c\u51fa\u9053MV"},{"display_arrow":0,"card_display_type":1,"actionlog":{"act_code":554,"ext":"t:157|pos:1_8|cate:5023|c_type:157|page:1|type:25","luicode":"","fid":"106003type=25&t=3&disable_hot=1&filter_type=realtimehot","lfid":"","uicode":""},"title_flag_pic":"https:\/\/simg.s.weibo.com\/20201204_plus.png","pic":"https:\/\/simg.s.weibo.com\/20201204_entertainment_ranking_9.png","card_type":25,"scheme":"sinaweibo:\/\/pageinfo?containerid=106003type%3d25%26t%3d3%26disable_hot%3d1%26filter_type%3dfun&extparam=fun_more%3D1","desc":"\u5708\u5185\u70ed\u5ea66251 | \u51fa\u5708\u6307\u657010.1%","title_sub":"\u674e\u82f1\u7231\u72b6\u6001"},{"display_arrow":0,"card_display_type":1,"actionlog":{"act_code":554,"ext":"t:157|pos:1_9|cate:5023|c_type:157|page:1|type:25","luicode":"","fid":"106003type=25&t=3&disable_hot=1&filter_type=realtimehot","lfid":"","uicode":""},"title_flag_pic":"https:\/\/simg.s.weibo.com\/20201222_reduce_small1.png","pic":"https:\/\/simg.s.weibo.com\/20201204_entertainment_ranking_10.png","card_type":25,"scheme":"sinaweibo:\/\/pageinfo?containerid=106003type%3d25%26t%3d3%26disable_hot%3d1%26filter_type%3dfun&extparam=fun_more%3D1","desc":"\u5708\u5185\u70ed\u5ea66166 | \u51fa\u5708\u6307\u65704.4%","title_sub":"\u4f55\u6d1b\u6d1b\u6df1V\u897f\u88c5"}]},{"show_type":0,"display_arrow":1,"actionlog":{"act_code":554,"ext":"t:157|pos:1_10|c_type:157|button:1|cate:5023|more:1|page:1|type:25","luicode":"","fid":"106003type=25&t=3&disable_hot=1&filter_type=realtimehot","lfid":"","uicode":""},"scheme":"https:\/\/m.weibo.cn\/search?containerid=100103type%3D1%26t%3D10%26q%3D%23%E7%83%AD%E6%90%9C%E5%A8%B1%E4%B9%90%E6%A6%9C%23&isnewpage=1&extparam=&luicode=10000011&lfid=106003type%3D25%26t%3D3%26disable_hot%3D1%26filter_type%3Drealtimehot","desc":"\u5a31\u4e50\u52a8\u6001\u5982\u4f55\u4e0a\u70ed\u641c","card_type":6}]},{"actionlog":{"act_code":554,"ext":"t:113|pos:0|c_type:113|cate:10103|mpos:4|page:1|type:25","luicode":"","fid":"106003type=25&t=3&disable_hot=1&filter_type=realtimehot","lfid":"","uicode":""},"desc_extr":"\u597d\u53cb\u5708\u7684\u65b0\u9c9c\u70ed\u70b9","display_arrow":1,"card_type":4,"scheme":"https:\/\/m.weibo.cn\/p\/index?containerid=106003type%3D25%26filter_type%3Dfriends&luicode=10000011&lfid=106003type%3D25%26t%3D3%26disable_hot%3D1%26filter_type%3Drealtimehot","desc":"\u597d\u53cb\u70ed\u641c","pic":"https:\/\/simg.s.weibo.com\/20200414_%E5%A5%BD%E5%8F%8B%E7%83%AD%E6%90%9C%403x.png"},{"actionlog":{"act_code":554,"ext":"t:140|pos:0|c_type:140|cate:10103|mpos:4|page:1|type:25","luicode":"","fid":"106003type=25&t=3&disable_hot=1&filter_type=realtimehot","lfid":"","uicode":""},"desc_extr":"\u5168\u7f51\u6f6e\u7269\u5b9e\u65f6\u79cd\u8349","display_arrow":1,"card_type":4,"scheme":"https:\/\/m.weibo.cn\/p\/index?containerid=106003type%3D25%26t%3D3%26disable_hot%3D1%26filter_type%3Dmoderngoods%26category%3Dmaster&extparam=seat%3D1%26%26display_time%3D1610961193&luicode=10000011&lfid=106003type%3D25%26t%3D3%26disable_hot%3D1%26filter_type%3Drealtimehot","desc":"\u5fae\u535a\u6f6e\u7269","pic":"https:\/\/simg.s.weibo.com\/20200914__icon_72.png"}],"cardlistInfo":{"cardlist_head_cards":[{"head_data":{"show_navi_mask":false,"scheme":"sinaweibo:\/\/abc","show_title":false,"cover_url":"https:\/\/simg.s.weibo.com\/20181226161247_750_350.png","data_type":2001},"show_menu":true,"head_type":1,"head_type_name":"immersive","title_top":"\u5fae\u535a\u70ed\u641c"},{"channel_list":[{"must_show":1,"default_add":1,"id":1,"name":"\u70ed\u641c\u699c","scheme":"sinaweibo:\/\/pageinfo?containerid=106003type=25&t=3&disable_hot=1&filter_type=realtimehot&title=\u70ed\u641c\u699c&extparam=","containerid":"106003type=25&t=3&disable_hot=1&filter_type=realtimehot"},{"must_show":1,"default_add":1,"id":2,"name":"\u8981\u95fb\u699c","scheme":"sinaweibo:\/\/pageinfo?containerid=231648_-_3&title=\u70ed\u641c\u699c&extparam=","containerid":"231648_-_3"},{"must_show":1,"default_add":1,"id":3,"name":"\u540c\u57ce\u699c","scheme":"sinaweibo:\/\/pageinfo?containerid=106003type=25&t=3&disable_hot=1&filter_type=region&title=\u70ed\u641c\u699c&extparam=","containerid":"106003type=25&t=3&disable_hot=1&filter_type=region"}],"head_type_name":"channel_list","show_menu":false,"head_type":0}],"page_size":20,"can_shared":0,"share_mini":{"custom_appkey":"gh_b07486d03e61","hdImageUrl":"https:\/\/simg.s.weibo.com\/20201020_20200731_vivo20200731.jpg","custom_path":"pages\/index\/index?is_share=1&tab=0"},"cardlist_menus":[],"toolbar_menus":[{"actionlog":{"act_code":554,"ext":"seqid:16109611934900366641288|type:25|t:3|pos:1-0-0|q:|ext:&t=114&","luicode":"","fid":"106003type=25&t=3&disable_hot=1&filter_type=realtimehot","lfid":""},"title_color_dark":"#EA8011","params":{"scheme":"sinaweibo:\/\/abc"},"skip_format":1,"pic":"https:\/\/simg.s.weibo.com\/20200507_realtimehot_selected_default.png","pic_dark":"https:\/\/simg.s.weibo.com\/20200507_realtimehot_selected_dark.png","title_color":"#FF8200","name":"\u70ed\u641c","type":"link","scheme":"https:\/\/m.weibo.cn\/feature\/applink?scheme=sinaweibo%3A%2F%2Fabc"},{"actionlog":{"act_code":554,"ext":"seqid:16109611934900366641288|type:25|t:3|pos:1-0-0|q:|ext:&t=115&","luicode":"","fid":"106003type=25&t=3&disable_hot=1&filter_type=realtimehot","lfid":""},"title_color_dark":"#999999","params":{"scheme":"sinaweibo:\/\/pageinfo?containerid=231648_-_4&title=\u70ed\u8bae&extparam=seat%3D1%26position%3D%255B%255D%26display_time%3D1610961193"},"skip_format":1,"pic":"https:\/\/simg.s.weibo.com\/20200611_ht_default.png","pic_dark":"https:\/\/simg.s.weibo.com\/20200611_ht_dark.png","title_color":"#333333","name":"\u70ed\u8bae","type":"link","scheme":"https:\/\/m.weibo.cn\/p\/index?containerid=231648_-_4&title=%E7%83%AD%E8%AE%AE&extparam=seat%3D1%26position%3D%255B%255D%26display_time%3D1610961193&luicode=10000011&lfid=106003type%3D25%26t%3D3%26disable_hot%3D1%26filter_type%3Drealtimehot"},{"actionlog":{"act_code":554,"ext":"seqid:16109611934900366641288|type:25|t:3|pos:1-0-0|q:|ext:&t=116&","luicode":"","fid":"106003type=25&t=3&disable_hot=1&filter_type=realtimehot","lfid":""},"title_color_dark":"#999999","params":{"scheme":"sinaweibo:\/\/pageinfo?containerid=106003type%3D25%26t%3D3%26disable_hot%3D1%26filter_type%3Dmoderngoods%26category%3Dmaster&title=\u6f6e\u7269&extparam=seat%3D1%26position%3D%255B%255D%26display_time%3D1610961193"},"skip_format":1,"pic":"https:\/\/simg.s.weibo.com\/20200728_morden_goods_default.png","pic_dark":"https:\/\/simg.s.weibo.com\/20200728_morden_goods_dark.png","title_color":"#333333","name":"\u6f6e\u7269","type":"link","scheme":"https:\/\/m.weibo.cn\/p\/index?containerid=106003type%3D25%26t%3D3%26disable_hot%3D1%26filter_type%3Dmoderngoods%26category%3Dmaster&title=%E6%BD%AE%E7%89%A9&extparam=seat%3D1%26position%3D%255B%255D%26display_time%3D1610961193&luicode=10000011&lfid=106003type%3D25%26t%3D3%26disable_hot%3D1%26filter_type%3Drealtimehot"},{"actionlog":{"act_code":554,"ext":"seqid:16109611934900366641288|type:25|t:3|pos:1-0-0|q:|ext:&t=137&","luicode":"","fid":"106003type=25&t=3&disable_hot=1&filter_type=realtimehot","lfid":""},"title_color_dark":"#999999","params":{"scheme":"sinaweibo:\/\/pageinfo?containerid=231648_-_1&title=\u699c\u5355&extparam=seat%3D1%26position%3D%255B%255D%26display_time%3D1610961193"},"skip_format":1,"pic":"https:\/\/simg.s.weibo.com\/20200817_list_default.png","pic_dark":"https:\/\/simg.s.weibo.com\/20200817_list_dark.png","title_color":"#333333","name":"\u699c\u5355","type":"link","scheme":"https:\/\/m.weibo.cn\/p\/index?containerid=231648_-_1&title=%E6%A6%9C%E5%8D%95&extparam=seat%3D1%26position%3D%255B%255D%26display_time%3D1610961193&luicode=10000011&lfid=106003type%3D25%26t%3D3%26disable_hot%3D1%26filter_type%3Drealtimehot"}],"containerid":"106003type=25&t=3&disable_hot=1&filter_type=realtimehot","show_style":1,"total":20,"page_title":"\u5fae\u535a\u70ed\u641c","starttime":1610961193,"title_top":"\u5fae\u535a\u70ed\u641c","v_p":"42","page_type":"08","nick":"\u5fae\u535a\u70ed\u641c","page":null},"scheme":"sinaweibo:\/\/pageinfo?containerid=106003type%3D25%26t%3D3%26disable_hot%3D1%26filter_type%3Drealtimehot&_T_WM=57632434966&v_p=42&luicode=10000011&lfid=106003type%3D25%26t%3D3%26disable_hot%3D1%26filter_type%3Drealtimehot","showAppTips":0}}
